[
    {
        "alpha": 0.2388818080204276,
        "class": "car",
        "h": 1.493374934611064,
        "l": 4.271192224649242,
        "motion": 0,
        "object_id": "5",
        "occluded": 3,
        "truncated": 3,
        "w": 1.848008799317672,
        "x": -47.2236113998666,
        "y": -0.8313129572010063,
        "z": -1.307287207139943,
        "framename": "frame0061",
        "groupname": "20221219_group0061_mode1_480frames"
    },
    {
        "alpha": -2.892698841412854,
        "class": "car",
        "h": 1.519552340107117,
        "l": 4.262948487144955,
        "motion": 0,
        "object_id": "6",
        "occluded": 3,
        "truncated": 3,
        "w": 1.796320220862105,
        "x": -44.27970265123322,
        "y": 32.49134937446838,
        "z": -1.981018874938131,
        "framename": "frame0061",
        "groupname": "20221219_group0061_mode1_480frames"
    },
    {
        "alpha": -2.93620369209046,
        "class": "motorcycle",
        "h": 1.179673011144737,
        "l": 1.773230748908742,
        "motion": 0,
        "object_id": "7",
        "occluded": 3,
        "truncated": 3,
        "w": 0.7827812386477958,
        "x": -52.52053001885199,
        "y": 13.19958172884302,
        "z": -1.693039765185422,
        "framename": "frame0061",
        "groupname": "20221219_group0061_mode1_480frames"
    },
    {
        "alpha": -1.91803464187483,
        "class": "cyclist",
        "h": 1.70152960962324,
        "l": 1.775877445000994,
        "motion": 1,
        "object_id": "16",
        "occluded": 3,
        "truncated": 3,
        "w": 0.7910204666308115,
        "x": 38.81305254801747,
        "y": 36.54507997250825,
        "z": -2.603995948569884,
        "framename": "frame0061",
        "groupname": "20221219_group0061_mode1_480frames"
    }
]