[
    {
        "alpha": 1.615005538496856,
        "class": "pedestrian",
        "h": 1.564549361687361,
        "l": 0.8974576654401214,
        "motion": 1,
        "object_id": "7",
        "occluded": 3,
        "truncated": 3,
        "w": 0.755191765390996,
        "x": -14.00116789156982,
        "y": 7.840444327607898,
        "z": -1.197920640723417,
        "framename": "frame0075",
        "groupname": "20221220_group0024_mode4_239frames"
    },
    {
        "alpha": 1.600071800437315,
        "class": "car",
        "h": 1.713701920406731,
        "l": 4.210148956028689,
        "motion": 1,
        "object_id": "14",
        "occluded": 0,
        "truncated": 0,
        "w": 2.144710202616318,
        "x": -0.2934060601121654,
        "y": 7.502388090883427,
        "z": -1.341214233059225,
        "framename": "frame0075",
        "groupname": "20221220_group0024_mode4_239frames"
    },
    {
        "alpha": 1.620215098880385,
        "class": "car",
        "h": 1.493311637625816,
        "l": 4.21014895602869,
        "motion": 1,
        "object_id": "15",
        "occluded": 1,
        "truncated": 0,
        "w": 1.862515479622766,
        "x": 2.161956615880641,
        "y": 32.68311480420549,
        "z": -2.063942317015449,
        "framename": "frame0075",
        "groupname": "20221220_group0024_mode4_239frames"
    },
    {
        "alpha": 1.361923058003949,
        "class": "pedestrian",
        "h": 1.63878305544784,
        "l": 1.028649299056114,
        "motion": 0,
        "object_id": "36",
        "occluded": 3,
        "truncated": 3,
        "w": 0.6748838558523159,
        "x": 15.5493324103763,
        "y": 10.79202392603698,
        "z": -1.373088145367954,
        "framename": "frame0075",
        "groupname": "20221220_group0024_mode4_239frames"
    },
    {
        "alpha": 1.599664122753612,
        "class": "motorcyclist",
        "h": 1.550044603903327,
        "l": 1.855516282857456,
        "motion": 1,
        "object_id": "37",
        "occluded": 0,
        "truncated": 0,
        "w": 0.8391268778658587,
        "x": 7.015517636363857,
        "y": 33.89042100232774,
        "z": -2.010965578242581,
        "framename": "frame0075",
        "groupname": "20221220_group0024_mode4_239frames"
    },
    {
        "alpha": 1.616021572022535,
        "class": "motorcyclist",
        "h": 1.5183265209198,
        "l": 1.804715516869091,
        "motion": 0,
        "object_id": "40",
        "occluded": 0,
        "truncated": 0,
        "w": 0.8887108214170861,
        "x": -11.70350377057106,
        "y": 36.51147103163007,
        "z": -1.758350244129633,
        "framename": "frame0075",
        "groupname": "20221220_group0024_mode4_239frames"
    },
    {
        "alpha": -1.517615442746563,
        "class": "car",
        "h": 1.576798685130131,
        "l": 4.231696260786295,
        "motion": 1,
        "object_id": "41",
        "occluded": 3,
        "truncated": 0,
        "w": 1.933177324407554,
        "x": -8.732751473866184,
        "y": 66.00234628122344,
        "z": -2.665066964964173,
        "framename": "frame0075",
        "groupname": "20221220_group0024_mode4_239frames"
    },
    {
        "alpha": 1.611093218820823,
        "class": "motorcyclist",
        "h": 1.571810334622669,
        "l": 1.855516282857456,
        "motion": 1,
        "object_id": "46",
        "occluded": 0,
        "truncated": 0,
        "w": 0.8391268778658585,
        "x": 8.136554960012417,
        "y": 28.73211485902087,
        "z": -1.923777626694553,
        "framename": "frame0075",
        "groupname": "20221220_group0024_mode4_239frames"
    },
    {
        "alpha": 0.06403809845030889,
        "class": "motorcycle",
        "h": 1.247707344721114,
        "l": 1.868093031716103,
        "motion": 0,
        "object_id": "50",
        "occluded": 3,
        "truncated": 3,
        "w": 0.7861550767235812,
        "x": 13.87286885412016,
        "y": 3.380211765252199,
        "z": -1.440636522430563,
        "framename": "frame0075",
        "groupname": "20221220_group0024_mode4_239frames"
    },
    {
        "alpha": -0.2007712372524886,
        "class": "motorcycle",
        "h": 1.36025492342094,
        "l": 2.13383485361389,
        "motion": 0,
        "object_id": "51",
        "occluded": 3,
        "truncated": 3,
        "w": 1.07935241992775,
        "x": 13.55588601941379,
        "y": 8.429426787273265,
        "z": -1.515026081081235,
        "framename": "frame0075",
        "groupname": "20221220_group0024_mode4_239frames"
    },
    {
        "alpha": -0.7988956659527505,
        "class": "motorcycle",
        "h": 1.320926541248129,
        "l": 1.800454903569856,
        "motion": 0,
        "object_id": "52",
        "occluded": 3,
        "truncated": 3,
        "w": 1.0192370835256,
        "x": -10.12920977767676,
        "y": 9.434908555106945,
        "z": -1.453994675585093,
        "framename": "frame0075",
        "groupname": "20221220_group0024_mode4_239frames"
    },
    {
        "alpha": -1.52658711489742,
        "class": "motorcyclist",
        "h": 1.659081254189618,
        "l": 1.804715516869091,
        "motion": 1,
        "object_id": "56",
        "occluded": 3,
        "truncated": 3,
        "w": 0.8887108214170861,
        "x": -12.44869017195256,
        "y": 3.032679473612015,
        "z": -1.104468483558703,
        "framename": "frame0075",
        "groupname": "20221220_group0024_mode4_239frames"
    },
    {
        "alpha": -1.091811373613244,
        "class": "motorcyclist",
        "h": 1.637364005957012,
        "l": 1.840065013078913,
        "motion": 1,
        "object_id": "59",
        "occluded": 0,
        "truncated": 0,
        "w": 0.8622270836853727,
        "x": -15.1582802684789,
        "y": 42.32810206819689,
        "z": -2.0247752612772,
        "framename": "frame0075",
        "groupname": "20221220_group0024_mode4_239frames"
    },
    {
        "alpha": 3.062026548929627,
        "class": "motorcyclist",
        "h": 1.493758079044572,
        "l": 1.979940915915706,
        "motion": 1,
        "object_id": "60",
        "occluded": 0,
        "truncated": 0,
        "w": 0.8622270836853734,
        "x": -17.27417362574078,
        "y": 48.82998356477152,
        "z": -2.186378636752292,
        "framename": "frame0075",
        "groupname": "20221220_group0024_mode4_239frames"
    },
    {
        "alpha": -0.03077136090828449,
        "class": "motorcycle",
        "h": 1.27508391343603,
        "l": 1.93633041555618,
        "motion": 0,
        "object_id": "62",
        "occluded": 3,
        "truncated": 3,
        "w": 0.8476272454253262,
        "x": 13.13319631860728,
        "y": 12.86655252125534,
        "z": -1.667832190584367,
        "framename": "frame0075",
        "groupname": "20221220_group0024_mode4_239frames"
    },
    {
        "alpha": 0.001565714344960363,
        "class": "motorcycle",
        "h": 1.324631779385724,
        "l": 1.80393175466345,
        "motion": 0,
        "object_id": "63",
        "occluded": 3,
        "truncated": 3,
        "w": 0.8476272454253262,
        "x": 13.11471250613358,
        "y": 14.18567493171095,
        "z": -1.652477900724003,
        "framename": "frame0075",
        "groupname": "20221220_group0024_mode4_239frames"
    },
    {
        "alpha": 0.2343917470722553,
        "class": "motorcycle",
        "h": 1.365932945712225,
        "l": 1.80393175466345,
        "motion": 0,
        "object_id": "64",
        "occluded": 3,
        "truncated": 3,
        "w": 0.8476272454253262,
        "x": 13.00314463772244,
        "y": 16.15392276547654,
        "z": -1.675402288510741,
        "framename": "frame0075",
        "groupname": "20221220_group0024_mode4_239frames"
    },
    {
        "alpha": 0.5822620920075353,
        "class": "car",
        "h": 1.533573145166919,
        "l": 4.201756013529428,
        "motion": 1,
        "object_id": "68",
        "occluded": 0,
        "truncated": 0,
        "w": 1.835080006347705,
        "x": -4.711273836853885,
        "y": 55.48206618722825,
        "z": -2.49089057269502,
        "framename": "frame0075",
        "groupname": "20221220_group0024_mode4_239frames"
    },
    {
        "alpha": 0.01543312568639135,
        "class": "motorcycle",
        "h": 1.137275112989897,
        "l": 1.80393175466345,
        "motion": 0,
        "object_id": "72",
        "occluded": 3,
        "truncated": 3,
        "w": 0.853642268655297,
        "x": 17.2099690083631,
        "y": 1.885084306673495,
        "z": -1.424771209325407,
        "framename": "frame0075",
        "groupname": "20221220_group0024_mode4_239frames"
    },
    {
        "alpha": 1.552215052398074,
        "class": "car",
        "h": 1.493311637625816,
        "l": 4.210148956028691,
        "motion": 1,
        "object_id": "73",
        "occluded": 3,
        "truncated": 0,
        "w": 1.802262576970093,
        "x": -0.4278644774051086,
        "y": 24.79795838318886,
        "z": -1.838681371496692,
        "framename": "frame0075",
        "groupname": "20221220_group0024_mode4_239frames"
    },
    {
        "alpha": -0.01264528588949811,
        "class": "motorcycle",
        "h": 1.36025492342094,
        "l": 1.80393175466345,
        "motion": 0,
        "object_id": "75",
        "occluded": 3,
        "truncated": 3,
        "w": 1.033104798410239,
        "x": 16.81245956765606,
        "y": 7.186924249404227,
        "z": -1.444081173061595,
        "framename": "frame0075",
        "groupname": "20221220_group0024_mode4_239frames"
    },
    {
        "alpha": -0.01264528588949811,
        "class": "motorcycle",
        "h": 1.414144190773371,
        "l": 1.605731527541629,
        "motion": 0,
        "object_id": "76",
        "occluded": 3,
        "truncated": 3,
        "w": 0.7039985604875949,
        "x": 17.01770467754533,
        "y": 8.284112751773348,
        "z": -1.425173188797173,
        "framename": "frame0075",
        "groupname": "20221220_group0024_mode4_239frames"
    },
    {
        "alpha": 0.07918328688532872,
        "class": "motorcycle",
        "h": 1.303072393449094,
        "l": 1.944998718208456,
        "motion": 0,
        "object_id": "77",
        "occluded": 3,
        "truncated": 3,
        "w": 0.8043088869139915,
        "x": 13.0920101713856,
        "y": 11.99002384604358,
        "z": -1.635838021566721,
        "framename": "frame0075",
        "groupname": "20221220_group0024_mode4_239frames"
    },
    {
        "alpha": 1.629141525803645,
        "class": "car",
        "h": 1.837046781251342,
        "l": 4.364649835149008,
        "motion": 1,
        "object_id": "78",
        "occluded": 2,
        "truncated": 0,
        "w": 2.015599218166518,
        "x": 2.81580144161869,
        "y": 19.57299312467552,
        "z": -1.571600969516506,
        "framename": "frame0075",
        "groupname": "20221220_group0024_mode4_239frames"
    },
    {
        "alpha": 1.600636126568312,
        "class": "motorcyclist",
        "h": 1.470618779523973,
        "l": 1.855516282857455,
        "motion": 1,
        "object_id": "81",
        "occluded": 0,
        "truncated": 0,
        "w": 0.8391268778658584,
        "x": 9.266302193728611,
        "y": 38.08091366076389,
        "z": -2.168253143246958,
        "framename": "frame0075",
        "groupname": "20221220_group0024_mode4_239frames"
    },
    {
        "alpha": 1.619560906475632,
        "class": "car",
        "h": 1.555918623387185,
        "l": 4.210148956028688,
        "motion": 1,
        "object_id": "82",
        "occluded": 3,
        "truncated": 0,
        "w": 1.860317277844156,
        "x": -0.8635957441338138,
        "y": 16.0602938906752,
        "z": -1.66976027845726,
        "framename": "frame0075",
        "groupname": "20221220_group0024_mode4_239frames"
    },
    {
        "alpha": -2.953702738531125,
        "class": "motorcycle",
        "h": 1.308183578659213,
        "l": 1.80393175466345,
        "motion": 0,
        "object_id": "85",
        "occluded": 3,
        "truncated": 3,
        "w": 0.887444255338192,
        "x": 12.85449789938873,
        "y": 19.66075501314061,
        "z": -1.773552343460481,
        "framename": "frame0075",
        "groupname": "20221220_group0024_mode4_239frames"
    },
    {
        "alpha": 1.572475795250153,
        "class": "pedestrian",
        "h": 1.625915881841608,
        "l": 0.4467755201279323,
        "motion": 1,
        "object_id": "86",
        "occluded": 0,
        "truncated": 0,
        "w": 0.5316912737681742,
        "x": -11.58323626207689,
        "y": 44.36146836663606,
        "z": -1.900306337989464,
        "framename": "frame0075",
        "groupname": "20221220_group0024_mode4_239frames"
    },
    {
        "alpha": -3.066476116916172,
        "class": "motorcyclist",
        "h": 1.76987905732815,
        "l": 1.840065013078912,
        "motion": 1,
        "object_id": "87",
        "occluded": 0,
        "truncated": 0,
        "w": 0.8622270836853723,
        "x": -4.346313616180139,
        "y": 46.52481183039808,
        "z": -2.123813882739011,
        "framename": "frame0075",
        "groupname": "20221220_group0024_mode4_239frames"
    },
    {
        "alpha": -2.890873920292516,
        "class": "motorcyclist",
        "h": 1.690854082932537,
        "l": 1.840065013078912,
        "motion": 1,
        "object_id": "88",
        "occluded": 0,
        "truncated": 0,
        "w": 0.8622270836853725,
        "x": -10.55830058850902,
        "y": 46.17441462851287,
        "z": -2.099632997209295,
        "framename": "frame0075",
        "groupname": "20221220_group0024_mode4_239frames"
    },
    {
        "alpha": -3.066476116916172,
        "class": "motorcyclist",
        "h": 1.561530327097,
        "l": 1.907083482053032,
        "motion": 1,
        "object_id": "89",
        "occluded": 0,
        "truncated": 0,
        "w": 0.8622270836853723,
        "x": -4.059360945411338,
        "y": 47.99834310763033,
        "z": -2.205765146205803,
        "framename": "frame0075",
        "groupname": "20221220_group0024_mode4_239frames"
    },
    {
        "alpha": -3.066476116916175,
        "class": "motorcyclist",
        "h": 1.619766213257733,
        "l": 1.840065013078912,
        "motion": 1,
        "object_id": "90",
        "occluded": 0,
        "truncated": 0,
        "w": 0.8622270836853724,
        "x": -6.819777401582845,
        "y": 48.05728171460073,
        "z": -2.214250599667266,
        "framename": "frame0075",
        "groupname": "20221220_group0024_mode4_239frames"
    },
    {
        "alpha": -1.50526320032927,
        "class": "car",
        "h": 1.783854159664017,
        "l": 4.231696260786294,
        "motion": 1,
        "object_id": "92",
        "occluded": 3,
        "truncated": 0,
        "w": 1.845721999514235,
        "x": -8.823613011755246,
        "y": 73.83763851611845,
        "z": -2.541611090217971,
        "framename": "frame0075",
        "groupname": "20221220_group0024_mode4_239frames"
    },
    {
        "alpha": -0.02000766125708899,
        "class": "motorcycle",
        "h": 1.40555539605418,
        "l": 1.852191167403508,
        "motion": 0,
        "object_id": "95",
        "occluded": 3,
        "truncated": 3,
        "w": 0.9101810108445602,
        "x": 16.76367726847386,
        "y": 2.767925480375424,
        "z": -1.337802552953798,
        "framename": "frame0075",
        "groupname": "20221220_group0024_mode4_239frames"
    },
    {
        "alpha": 0.03869579686139293,
        "class": "motorcycle",
        "h": 1.357183041613284,
        "l": 1.80393175466345,
        "motion": 0,
        "object_id": "96",
        "occluded": 3,
        "truncated": 3,
        "w": 0.8476272454253262,
        "x": 12.67646369352597,
        "y": 17.59627842191903,
        "z": -1.75325738367811,
        "framename": "frame0075",
        "groupname": "20221220_group0024_mode4_239frames"
    },
    {
        "alpha": 2.933723714054619,
        "class": "pedestrian",
        "h": 1.164170913303053,
        "l": 0.7259525808371677,
        "motion": 0,
        "object_id": "97",
        "occluded": 3,
        "truncated": 3,
        "w": 0.6212385351000603,
        "x": 18.0358446674215,
        "y": 4.061999848052976,
        "z": -1.447117620459461,
        "framename": "frame0075",
        "groupname": "20221220_group0024_mode4_239frames"
    },
    {
        "alpha": 1.611093218820823,
        "class": "motorcyclist",
        "h": 1.571810334622669,
        "l": 1.855516282857456,
        "motion": 1,
        "object_id": "102",
        "occluded": 0,
        "truncated": 0,
        "w": 0.8391268778658585,
        "x": 8.696882415063042,
        "y": 33.21533162505285,
        "z": -2.003788608994458,
        "framename": "frame0075",
        "groupname": "20221220_group0024_mode4_239frames"
    },
    {
        "alpha": 1.616537545953326,
        "class": "car",
        "h": 1.493311637625816,
        "l": 4.210148956028688,
        "motion": 1,
        "object_id": "104",
        "occluded": 3,
        "truncated": 0,
        "w": 1.862515479622765,
        "x": -0.4241395167935418,
        "y": 33.29322276708735,
        "z": -1.999730344885607,
        "framename": "frame0075",
        "groupname": "20221220_group0024_mode4_239frames"
    },
    {
        "alpha": -2.796509991872282,
        "class": "car",
        "h": 1.614400469927532,
        "l": 4.236791506666847,
        "motion": 1,
        "object_id": "105",
        "occluded": 2,
        "truncated": 0,
        "w": 1.876266371085774,
        "x": 5.815588515738813,
        "y": 46.63121939222547,
        "z": -2.286202824312828,
        "framename": "frame0075",
        "groupname": "20221220_group0024_mode4_239frames"
    },
    {
        "alpha": 0.4669255755037246,
        "class": "motorcyclist",
        "h": 1.52598774363458,
        "l": 1.855516282857456,
        "motion": 1,
        "object_id": "106",
        "occluded": 3,
        "truncated": 3,
        "w": 0.8654067222153418,
        "x": 18.76408273516356,
        "y": 28.20698639643349,
        "z": -1.849003966410345,
        "framename": "frame0075",
        "groupname": "20221220_group0024_mode4_239frames"
    },
    {
        "alpha": -1.309190961637969,
        "class": "pedestrian",
        "h": 1.270206985658428,
        "l": 1.010414920244099,
        "motion": 0,
        "object_id": "108",
        "occluded": 3,
        "truncated": 3,
        "w": 0.5145081776867427,
        "x": 17.29066574156606,
        "y": 12.65675310082674,
        "z": -1.603159979679182,
        "framename": "frame0075",
        "groupname": "20221220_group0024_mode4_239frames"
    },
    {
        "alpha": 1.706619785567687,
        "class": "pedestrian",
        "h": 1.511741631075699,
        "l": 0.7647264309461093,
        "motion": 1,
        "object_id": "109",
        "occluded": 0,
        "truncated": 0,
        "w": 0.6921979150425385,
        "x": -15.35458057334485,
        "y": 63.20206809359043,
        "z": -2.30046563851396,
        "framename": "frame0075",
        "groupname": "20221220_group0024_mode4_239frames"
    },
    {
        "alpha": 0.1455011777513699,
        "class": "motorcycle",
        "h": 1.357183041613284,
        "l": 1.80393175466345,
        "motion": 0,
        "object_id": "112",
        "occluded": 3,
        "truncated": 3,
        "w": 0.8476272454253263,
        "x": 12.22827874005728,
        "y": 20.66225759537857,
        "z": -1.77598885842694,
        "framename": "frame0075",
        "groupname": "20221220_group0024_mode4_239frames"
    },
    {
        "alpha": 1.572164066276068,
        "class": "car",
        "h": 1.801002092401322,
        "l": 4.570651007309432,
        "motion": 1,
        "object_id": "113",
        "occluded": 2,
        "truncated": 2,
        "w": 2.144710202616318,
        "x": 2.898483675019667,
        "y": 7.346082842099913,
        "z": -1.349575250138082,
        "framename": "frame0075",
        "groupname": "20221220_group0024_mode4_239frames"
    },
    {
        "alpha": 1.218502188602281,
        "class": "car",
        "h": 1.525115925929704,
        "l": 4.124959806658064,
        "motion": 0,
        "object_id": "114",
        "occluded": 3,
        "truncated": 3,
        "w": 1.852257674778364,
        "x": 14.30495797323449,
        "y": 29.55816287147704,
        "z": -1.792261989994873,
        "framename": "frame0075",
        "groupname": "20221220_group0024_mode4_239frames"
    },
    {
        "alpha": 0.1408435062630563,
        "class": "truck",
        "h": 2.82861815092208,
        "l": 6.743639326908784,
        "motion": 1,
        "object_id": "115",
        "occluded": 1,
        "truncated": 0,
        "w": 2.89411628707494,
        "x": -17.1363011363268,
        "y": 52.70096782476999,
        "z": -1.487468510098319,
        "framename": "frame0075",
        "groupname": "20221220_group0024_mode4_239frames"
    },
    {
        "alpha": -0.634785950006626,
        "class": "motorcycle",
        "h": 1.320926541248129,
        "l": 1.800454903569856,
        "motion": 0,
        "object_id": "118",
        "occluded": 1,
        "truncated": 0,
        "w": 1.0192370835256,
        "x": -10.71100532716107,
        "y": 32.76601128474257,
        "z": -1.923056606178192,
        "framename": "frame0075",
        "groupname": "20221220_group0024_mode4_239frames"
    },
    {
        "alpha": -3.066476116916172,
        "class": "motorcyclist",
        "h": 1.561530327097,
        "l": 1.907083482053032,
        "motion": 1,
        "object_id": "119",
        "occluded": 0,
        "truncated": 0,
        "w": 0.8622270836853723,
        "x": -1.573495497025925,
        "y": 47.43967155195744,
        "z": -2.29767618937031,
        "framename": "frame0075",
        "groupname": "20221220_group0024_mode4_239frames"
    },
    {
        "alpha": 0.4669255755037246,
        "class": "motorcyclist",
        "h": 1.52598774363458,
        "l": 1.855516282857456,
        "motion": 1,
        "object_id": "120",
        "occluded": 3,
        "truncated": 3,
        "w": 0.8654067222153418,
        "x": 16.67743372418661,
        "y": 26.91194063477984,
        "z": -2.05109676385061,
        "framename": "frame0075",
        "groupname": "20221220_group0024_mode4_239frames"
    }
]