[
    {
        "alpha": 1.606007203352796,
        "class": "car",
        "h": 1.811716865397702,
        "l": 4.246451549816979,
        "motion": 1,
        "object_id": "4",
        "occluded": 0,
        "truncated": 0,
        "w": 2.014637523865322,
        "x": -2.824418108891872,
        "y": 71.58968308907983,
        "z": -0.3141003751428194,
        "framename": "frame0087",
        "groupname": "20221224_group0043_mode2_229frames"
    },
    {
        "alpha": -1.52881209285372,
        "class": "car",
        "h": 1.687307123567816,
        "l": 4.246451549816979,
        "motion": 1,
        "object_id": "7",
        "occluded": 0,
        "truncated": 0,
        "w": 1.928204208693897,
        "x": -22.71554558451828,
        "y": 51.84055637394088,
        "z": -1.143374190654034,
        "framename": "frame0087",
        "groupname": "20221224_group0043_mode2_229frames"
    },
    {
        "alpha": -1.536367914240216,
        "class": "car",
        "h": 1.551476474703942,
        "l": 4.660325970398186,
        "motion": 1,
        "object_id": "10",
        "occluded": 1,
        "truncated": 0,
        "w": 1.903078855389662,
        "x": -50.96605397198759,
        "y": 87.84545369497164,
        "z": -1.261382288152669,
        "framename": "frame0087",
        "groupname": "20221224_group0043_mode2_229frames"
    },
    {
        "alpha": -1.536367914240215,
        "class": "car",
        "h": 1.49446030476116,
        "l": 4.341671203191473,
        "motion": 1,
        "object_id": "11",
        "occluded": 1,
        "truncated": 0,
        "w": 1.798870242389162,
        "x": -50.39202713920057,
        "y": 81.02996254421787,
        "z": -1.499336592604786,
        "framename": "frame0087",
        "groupname": "20221224_group0043_mode2_229frames"
    },
    {
        "alpha": -0.4061035730829364,
        "class": "bus",
        "h": 3.464306984229539,
        "l": 12.39050418675129,
        "motion": 1,
        "object_id": "13",
        "occluded": 3,
        "truncated": 3,
        "w": 2.988834579789402,
        "x": -42.29181380318055,
        "y": 58.34587834464273,
        "z": -0.3859628558879999,
        "framename": "frame0087",
        "groupname": "20221224_group0043_mode2_229frames"
    },
    {
        "alpha": -1.595499443141467,
        "class": "pedestrian",
        "h": 1.658432078674226,
        "l": 0.6267352474001451,
        "motion": 0,
        "object_id": "15",
        "occluded": 0,
        "truncated": 0,
        "w": 0.7417039972169116,
        "x": 16.53965946329169,
        "y": 38.48320019558891,
        "z": -0.6423901922427919,
        "framename": "frame0087",
        "groupname": "20221224_group0043_mode2_229frames"
    }
]