[
    {
        "alpha": 1.627133729300118,
        "class": "car",
        "h": 1.828262726053849,
        "l": 4.051541989199943,
        "motion": 1,
        "object_id": "1",
        "occluded": 0,
        "truncated": 0,
        "w": 1.855458909487261,
        "x": -4.372439704676635,
        "y": 39.87181343913706,
        "z": -2.147835067773858,
        "framename": "frame0001",
        "groupname": "20221220_group0044_mode2_148frames"
    },
    {
        "alpha": 1.627133729300118,
        "class": "car",
        "h": 1.619800099270119,
        "l": 4.329759464853158,
        "motion": 1,
        "object_id": "2",
        "occluded": 0,
        "truncated": 0,
        "w": 2.155534728832296,
        "x": -0.6981169527769991,
        "y": 40.03951832720929,
        "z": -2.211130103476564,
        "framename": "frame0001",
        "groupname": "20221220_group0044_mode2_148frames"
    }
]