[
    {
        "alpha": 1.592547583095531,
        "class": "car",
        "h": 1.511615700625811,
        "l": 4.539162031083775,
        "motion": 1,
        "object_id": "1",
        "occluded": 0,
        "truncated": 0,
        "w": 2.069940723564077,
        "x": 3.136603998898676,
        "y": 22.96344052807128,
        "z": -1.831106701738855,
        "framename": "frame0116",
        "groupname": "20221221_group0012_mode1_370frames"
    },
    {
        "alpha": -1.538281523597,
        "class": "car",
        "h": 1.543449718953175,
        "l": 4.177955503411329,
        "motion": 1,
        "object_id": "7",
        "occluded": 0,
        "truncated": 0,
        "w": 2.069940723564077,
        "x": -17.64819048272283,
        "y": 79.14109737471085,
        "z": -3.446363063605158,
        "framename": "frame0116",
        "groupname": "20221221_group0012_mode1_370frames"
    }
]