[
    {
        "alpha": -1.537323281402349,
        "class": "car",
        "h": 1.470569006247876,
        "l": 4.426390051216977,
        "motion": 0,
        "object_id": "6",
        "occluded": 3,
        "truncated": 3,
        "w": 1.942033072186503,
        "x": -11.36858338771486,
        "y": 2.951290344693025,
        "z": -1.313268823702899,
        "framename": "frame0026",
        "groupname": "20221221_group0077_mode2_231frames"
    },
    {
        "alpha": -1.534708476084995,
        "class": "car",
        "h": 1.603723627316654,
        "l": 4.279803509012275,
        "motion": 0,
        "object_id": "7",
        "occluded": 0,
        "truncated": 1,
        "w": 1.966848674202408,
        "x": -12.13860945843551,
        "y": 12.91792689636344,
        "z": -1.529073628018165,
        "framename": "frame0026",
        "groupname": "20221221_group0077_mode2_231frames"
    },
    {
        "alpha": 0.08179302614621572,
        "class": "motorcycle",
        "h": 1.157170532624776,
        "l": 1.940453664783724,
        "motion": 0,
        "object_id": "20",
        "occluded": 3,
        "truncated": 3,
        "w": 0.7952169158351254,
        "x": -19.54488302316922,
        "y": 13.07750476980461,
        "z": -1.42354581918279,
        "framename": "frame0026",
        "groupname": "20221221_group0077_mode2_231frames"
    },
    {
        "alpha": -1.527707150759991,
        "class": "pedestrian",
        "h": 1.653183651787526,
        "l": 0.556465730524333,
        "motion": 1,
        "object_id": "23",
        "occluded": 3,
        "truncated": 3,
        "w": 0.6847147900194673,
        "x": 22.17529884816344,
        "y": 37.6815455111436,
        "z": -2.324792592533758,
        "framename": "frame0026",
        "groupname": "20221221_group0077_mode2_231frames"
    },
    {
        "alpha": -2.207603525247282,
        "class": "motorcycle",
        "h": 1.430344623324804,
        "l": 1.851694626225186,
        "motion": 0,
        "object_id": "25",
        "occluded": 3,
        "truncated": 3,
        "w": 0.6193841691624444,
        "x": -27.06582154240946,
        "y": 44.06673065703197,
        "z": -1.779682728529677,
        "framename": "frame0026",
        "groupname": "20221221_group0077_mode2_231frames"
    },
    {
        "alpha": 2.643573040817799,
        "class": "motorcycle",
        "h": 1.139006798381556,
        "l": 1.708954556113354,
        "motion": 0,
        "object_id": "26",
        "occluded": 1,
        "truncated": 0,
        "w": 0.7381040067493737,
        "x": -26.93177143492539,
        "y": 46.62068548113616,
        "z": -1.778546170076517,
        "framename": "frame0026",
        "groupname": "20221221_group0077_mode2_231frames"
    },
    {
        "alpha": 0.1047319930355447,
        "class": "motorcycle",
        "h": 1.302618785062247,
        "l": 1.940453664783724,
        "motion": 0,
        "object_id": "27",
        "occluded": 1,
        "truncated": 1,
        "w": 0.7229523797156558,
        "x": -19.36813156138777,
        "y": 12.23086345319855,
        "z": -1.454994496947709,
        "framename": "frame0026",
        "groupname": "20221221_group0077_mode2_231frames"
    },
    {
        "alpha": 0.0838648136797828,
        "class": "motorcycle",
        "h": 1.047514992652658,
        "l": 1.869244355984322,
        "motion": 0,
        "object_id": "28",
        "occluded": 3,
        "truncated": 3,
        "w": 0.6981486066230915,
        "x": -19.35004437892421,
        "y": 15.62586691275278,
        "z": -1.466308194340975,
        "framename": "frame0026",
        "groupname": "20221221_group0077_mode2_231frames"
    },
    {
        "alpha": 0.0794525807432422,
        "class": "motorcycle",
        "h": 1.184261638521342,
        "l": 1.728430239978636,
        "motion": 0,
        "object_id": "30",
        "occluded": 3,
        "truncated": 3,
        "w": 0.7520978766309538,
        "x": -19.36028128340175,
        "y": 13.89339570038237,
        "z": -1.470521445706306,
        "framename": "frame0026",
        "groupname": "20221221_group0077_mode2_231frames"
    },
    {
        "alpha": 0.04867251143232312,
        "class": "motorcycle",
        "h": 1.157170532624776,
        "l": 1.904849010384023,
        "motion": 0,
        "object_id": "31",
        "occluded": 3,
        "truncated": 3,
        "w": 0.7050644122311507,
        "x": -20.11706522955599,
        "y": 34.40299603842517,
        "z": -1.981955097737537,
        "framename": "frame0026",
        "groupname": "20221221_group0077_mode2_231frames"
    },
    {
        "alpha": 0.09391343677333576,
        "class": "motorcycle",
        "h": 1.363808650762293,
        "l": 1.762896049289555,
        "motion": 0,
        "object_id": "33",
        "occluded": 3,
        "truncated": 3,
        "w": 0.6163451577372203,
        "x": -21.39221224063425,
        "y": 57.83919145283686,
        "z": -2.519665440329876,
        "framename": "frame0026",
        "groupname": "20221221_group0077_mode2_231frames"
    },
    {
        "alpha": 0.0562126656558252,
        "class": "motorcycle",
        "h": 1.091772495619202,
        "l": 1.638848488370352,
        "motion": 0,
        "object_id": "34",
        "occluded": 3,
        "truncated": 3,
        "w": 0.6567422511031502,
        "x": -20.17113115722378,
        "y": 35.21306593708127,
        "z": -2.004546349543282,
        "framename": "frame0026",
        "groupname": "20221221_group0077_mode2_231frames"
    },
    {
        "alpha": 0.05621266565582519,
        "class": "motorcycle",
        "h": 1.142460737718529,
        "l": 1.904849010384023,
        "motion": 0,
        "object_id": "35",
        "occluded": 3,
        "truncated": 3,
        "w": 0.8207435861934405,
        "x": -20.31246248149332,
        "y": 36.63087004437104,
        "z": -2.032759097802257,
        "framename": "frame0026",
        "groupname": "20221221_group0077_mode2_231frames"
    },
    {
        "alpha": 0.4625723972518819,
        "class": "cycle",
        "h": 1.027795925672474,
        "l": 1.717095674168701,
        "motion": 0,
        "object_id": "36",
        "occluded": 3,
        "truncated": 3,
        "w": 0.4993562694240404,
        "x": 19.29135527495336,
        "y": 9.206413307661641,
        "z": -1.889749236849464,
        "framename": "frame0026",
        "groupname": "20221221_group0077_mode2_231frames"
    },
    {
        "alpha": 0.0436926149013416,
        "class": "cycle",
        "h": 1.155356969956165,
        "l": 1.481752742157247,
        "motion": 0,
        "object_id": "184",
        "occluded": 3,
        "truncated": 3,
        "w": 0.4144199631529939,
        "x": 19.54293546251441,
        "y": 3.49055445155732,
        "z": -1.699336770453768,
        "framename": "frame0026",
        "groupname": "20221221_group0077_mode2_231frames"
    },
    {
        "alpha": 0.1791371676242567,
        "class": "motorcycle",
        "h": 1.344220445983503,
        "l": 1.850255206971148,
        "motion": 0,
        "object_id": "195",
        "occluded": 3,
        "truncated": 3,
        "w": 0.7040572474104526,
        "x": -18.98957239014565,
        "y": 3.375393121664452,
        "z": -1.06771987244273,
        "framename": "frame0026",
        "groupname": "20221221_group0077_mode2_231frames"
    },
    {
        "alpha": 0.116574730577186,
        "class": "motorcycle",
        "h": 1.274990208422121,
        "l": 1.878738930490909,
        "motion": 0,
        "object_id": "196",
        "occluded": 3,
        "truncated": 3,
        "w": 0.7478337352532723,
        "x": -18.95921042897962,
        "y": 4.724334643921306,
        "z": -1.154951715234059,
        "framename": "frame0026",
        "groupname": "20221221_group0077_mode2_231frames"
    },
    {
        "alpha": 0.1146645379334818,
        "class": "motorcycle",
        "h": 1.235591369363583,
        "l": 1.788540472678332,
        "motion": 0,
        "object_id": "198",
        "occluded": 3,
        "truncated": 3,
        "w": 0.6931131254497478,
        "x": -19.21724737692287,
        "y": 5.569222126173671,
        "z": -1.102140467466099,
        "framename": "frame0026",
        "groupname": "20221221_group0077_mode2_231frames"
    },
    {
        "alpha": 0.08575001573084708,
        "class": "motorcycle",
        "h": 1.201299917343517,
        "l": 1.940453664783724,
        "motion": 0,
        "object_id": "203",
        "occluded": 3,
        "truncated": 3,
        "w": 0.7898088243734358,
        "x": -19.77378666100445,
        "y": 16.41093808115733,
        "z": -1.370918846243583,
        "framename": "frame0026",
        "groupname": "20221221_group0077_mode2_231frames"
    },
    {
        "alpha": -0.01358696594371172,
        "class": "motorcycle",
        "h": 1.24650648490236,
        "l": 1.833356606473185,
        "motion": 0,
        "object_id": "208",
        "occluded": 3,
        "truncated": 3,
        "w": 0.7478337352532722,
        "x": -19.36734183755769,
        "y": 6.394405533667145,
        "z": -1.232410403869031,
        "framename": "frame0026",
        "groupname": "20221221_group0077_mode2_231frames"
    },
    {
        "alpha": 0.1077456842921276,
        "class": "motorcycle",
        "h": 1.277380810712466,
        "l": 1.857376137851088,
        "motion": 0,
        "object_id": "209",
        "occluded": 3,
        "truncated": 3,
        "w": 0.8207435861934405,
        "x": -20.16632454456432,
        "y": 27.28603902687342,
        "z": -1.737926986975854,
        "framename": "frame0026",
        "groupname": "20221221_group0077_mode2_231frames"
    },
    {
        "alpha": 0.09340295684836274,
        "class": "motorcycle",
        "h": 1.211158484760073,
        "l": 1.725598992902631,
        "motion": 0,
        "object_id": "210",
        "occluded": 3,
        "truncated": 3,
        "w": 0.7115951880359105,
        "x": -19.72346097134869,
        "y": 25.83851846198006,
        "z": -1.765000465855204,
        "framename": "frame0026",
        "groupname": "20221221_group0077_mode2_231frames"
    }
]