[
    {
        "alpha": 1.73145599575448,
        "class": "car",
        "h": 1.591980186578269,
        "l": 4.360903742732751,
        "motion": 1,
        "object_id": "1",
        "occluded": 0,
        "truncated": 0,
        "w": 1.852739452462225,
        "x": -0.09195148502799508,
        "y": 37.84589811913681,
        "z": -2.382578930910587,
        "framename": "frame0099",
        "groupname": "20221219_group0073_mode2_199frames"
    },
    {
        "alpha": 2.986077697077642,
        "class": "car",
        "h": 1.569329401666511,
        "l": 3.699046716452506,
        "motion": 1,
        "object_id": "15",
        "occluded": 3,
        "truncated": 3,
        "w": 1.760259610634246,
        "x": 45.96937954569549,
        "y": 2.072334852318086,
        "z": -1.103158706370435,
        "framename": "frame0099",
        "groupname": "20221219_group0073_mode2_199frames"
    },
    {
        "alpha": 1.018003768664333,
        "class": "car",
        "h": 1.596759519863538,
        "l": 4.222137263395603,
        "motion": 0,
        "object_id": "27",
        "occluded": 3,
        "truncated": 3,
        "w": 1.856565385285615,
        "x": 36.22590238917203,
        "y": 9.075569979624722,
        "z": -1.065551977170888,
        "framename": "frame0099",
        "groupname": "20221219_group0073_mode2_199frames"
    },
    {
        "alpha": 0.9217585497947479,
        "class": "car",
        "h": 1.596759519863538,
        "l": 4.222137263395602,
        "motion": 0,
        "object_id": "28",
        "occluded": 3,
        "truncated": 3,
        "w": 1.933319490961459,
        "x": 33.9336576335611,
        "y": 9.956306388250503,
        "z": -1.088941479838745,
        "framename": "frame0099",
        "groupname": "20221219_group0073_mode2_199frames"
    },
    {
        "alpha": 1.069408139848968,
        "class": "car",
        "h": 1.596759519863538,
        "l": 4.222137263395603,
        "motion": 0,
        "object_id": "29",
        "occluded": 3,
        "truncated": 3,
        "w": 1.856565385285615,
        "x": 31.57767567674583,
        "y": 10.83361974511616,
        "z": -1.067913976459685,
        "framename": "frame0099",
        "groupname": "20221219_group0073_mode2_199frames"
    },
    {
        "alpha": 0.9776296374009729,
        "class": "car",
        "h": 1.596759519863538,
        "l": 4.222137263395603,
        "motion": 0,
        "object_id": "30",
        "occluded": 3,
        "truncated": 3,
        "w": 1.911389746482647,
        "x": 29.27717191659321,
        "y": 12.28623312861086,
        "z": -1.120128535090535,
        "framename": "frame0099",
        "groupname": "20221219_group0073_mode2_199frames"
    },
    {
        "alpha": -2.091861046655889,
        "class": "car",
        "h": 1.85492842259346,
        "l": 5.303596382474449,
        "motion": 0,
        "object_id": "31",
        "occluded": 3,
        "truncated": 3,
        "w": 2.024338618590001,
        "x": 27.01033863856586,
        "y": 13.06737722117818,
        "z": -1.085731053847481,
        "framename": "frame0099",
        "groupname": "20221219_group0073_mode2_199frames"
    },
    {
        "alpha": -2.087004297193448,
        "class": "car",
        "h": 1.962498798730928,
        "l": 4.222137263395602,
        "motion": 0,
        "object_id": "32",
        "occluded": 3,
        "truncated": 3,
        "w": 2.037919718043852,
        "x": 24.67620754796167,
        "y": 14.18124716333602,
        "z": -1.093454309979876,
        "framename": "frame0099",
        "groupname": "20221219_group0073_mode2_199frames"
    },
    {
        "alpha": -2.079353386686753,
        "class": "car",
        "h": 2.048555099640902,
        "l": 4.501820241353019,
        "motion": 0,
        "object_id": "33",
        "occluded": 3,
        "truncated": 3,
        "w": 1.978587009312657,
        "x": 22.25748102893085,
        "y": 15.28730790197817,
        "z": -1.111620017364165,
        "framename": "frame0099",
        "groupname": "20221219_group0073_mode2_199frames"
    },
    {
        "alpha": -2.257447689041868,
        "class": "car",
        "h": 1.876335948896532,
        "l": 4.501820241353018,
        "motion": 0,
        "object_id": "34",
        "occluded": 3,
        "truncated": 3,
        "w": 1.879583380315482,
        "x": 20.2934286507377,
        "y": 16.76981703259074,
        "z": -1.278234338544362,
        "framename": "frame0099",
        "groupname": "20221219_group0073_mode2_199frames"
    },
    {
        "alpha": -2.372400376078113,
        "class": "car",
        "h": 1.653246282063056,
        "l": 4.50182024135302,
        "motion": 0,
        "object_id": "35",
        "occluded": 3,
        "truncated": 3,
        "w": 2.005145595570223,
        "x": 18.60238994632524,
        "y": 18.75879356385991,
        "z": -1.463970621304282,
        "framename": "frame0099",
        "groupname": "20221219_group0073_mode2_199frames"
    },
    {
        "alpha": -2.410074911568127,
        "class": "car",
        "h": 1.653246282063056,
        "l": 4.302611300066195,
        "motion": 0,
        "object_id": "36",
        "occluded": 3,
        "truncated": 3,
        "w": 1.820663177829282,
        "x": 16.8552539099652,
        "y": 20.42040661060778,
        "z": -1.484906323045586,
        "framename": "frame0099",
        "groupname": "20221219_group0073_mode2_199frames"
    },
    {
        "alpha": -2.52192428363455,
        "class": "car",
        "h": 1.653246282063056,
        "l": 4.302611300066194,
        "motion": 0,
        "object_id": "37",
        "occluded": 3,
        "truncated": 3,
        "w": 1.896348272287104,
        "x": 15.39185029927736,
        "y": 22.50717624838898,
        "z": -1.640106592159122,
        "framename": "frame0099",
        "groupname": "20221219_group0073_mode2_199frames"
    },
    {
        "alpha": -2.422579639127856,
        "class": "car",
        "h": 1.653246282063056,
        "l": 4.302611300066195,
        "motion": 0,
        "object_id": "38",
        "occluded": 0,
        "truncated": 0,
        "w": 2.113942918853342,
        "x": 13.17840296739279,
        "y": 29.01036686779795,
        "z": -1.750040187342909,
        "framename": "frame0099",
        "groupname": "20221219_group0073_mode2_199frames"
    },
    {
        "alpha": -2.354596083096217,
        "class": "car",
        "h": 1.653246282063056,
        "l": 4.302611300066195,
        "motion": 0,
        "object_id": "39",
        "occluded": 0,
        "truncated": 0,
        "w": 2.113942918853342,
        "x": 12.34852149415002,
        "y": 31.63744812075575,
        "z": -1.896104989945793,
        "framename": "frame0099",
        "groupname": "20221219_group0073_mode2_199frames"
    },
    {
        "alpha": -2.316894834484788,
        "class": "car",
        "h": 1.653246282063056,
        "l": 4.302611300066194,
        "motion": 0,
        "object_id": "40",
        "occluded": 0,
        "truncated": 0,
        "w": 1.872696680269033,
        "x": 11.35592969385076,
        "y": 37.32946726538358,
        "z": -2.030137883735895,
        "framename": "frame0099",
        "groupname": "20221219_group0073_mode2_199frames"
    },
    {
        "alpha": 2.466598283174139,
        "class": "car",
        "h": 1.588283412084529,
        "l": 4.377163783094037,
        "motion": 0,
        "object_id": "41",
        "occluded": 3,
        "truncated": 3,
        "w": 1.930142772506457,
        "x": 29.21988619346232,
        "y": 17.91343663730262,
        "z": -0.8366076337201742,
        "framename": "frame0099",
        "groupname": "20221219_group0073_mode2_199frames"
    },
    {
        "alpha": -1.115855110555859,
        "class": "car",
        "h": 1.578686684497948,
        "l": 4.320077639020544,
        "motion": 0,
        "object_id": "43",
        "occluded": 3,
        "truncated": 3,
        "w": 1.930142772506456,
        "x": 17.81723712485503,
        "y": 33.8756327864272,
        "z": -1.611580331931145,
        "framename": "frame0099",
        "groupname": "20221219_group0073_mode2_199frames"
    },
    {
        "alpha": 3.079273833677237,
        "class": "car",
        "h": 1.569329401666511,
        "l": 4.595458037519828,
        "motion": 1,
        "object_id": "50",
        "occluded": 3,
        "truncated": 3,
        "w": 1.841083442479732,
        "x": 50.77189438448055,
        "y": 1.637595593041369,
        "z": -1.065948013268314,
        "framename": "frame0099",
        "groupname": "20221219_group0073_mode2_199frames"
    },
    {
        "alpha": 1.628230898569563,
        "class": "car",
        "h": 1.596759519863538,
        "l": 4.222137263395602,
        "motion": 0,
        "object_id": "64",
        "occluded": 3,
        "truncated": 3,
        "w": 1.856565385285615,
        "x": 61.80754392037161,
        "y": 5.29821012636857,
        "z": -0.8544074677542683,
        "framename": "frame0099",
        "groupname": "20221219_group0073_mode2_199frames"
    },
    {
        "alpha": 1.536091790677823,
        "class": "car",
        "h": 1.596759519863538,
        "l": 4.222137263395603,
        "motion": 0,
        "object_id": "65",
        "occluded": 3,
        "truncated": 3,
        "w": 1.856565385285615,
        "x": 49.82409541909879,
        "y": 6.613011320628291,
        "z": -1.076263181718938,
        "framename": "frame0099",
        "groupname": "20221219_group0073_mode2_199frames"
    },
    {
        "alpha": 2.315834432628323,
        "class": "car",
        "h": 1.578686684497948,
        "l": 4.596094216150608,
        "motion": 0,
        "object_id": "75",
        "occluded": 3,
        "truncated": 0,
        "w": 1.930142772506457,
        "x": 22.38446294575915,
        "y": 27.40755405262539,
        "z": -1.465302026821391,
        "framename": "frame0099",
        "groupname": "20221219_group0073_mode2_199frames"
    },
    {
        "alpha": 2.315834432628323,
        "class": "car",
        "h": 1.578686684497948,
        "l": 4.596094216150608,
        "motion": 0,
        "object_id": "76",
        "occluded": 3,
        "truncated": 0,
        "w": 1.957244689836894,
        "x": 19.21951883017969,
        "y": 24.05509396913322,
        "z": -1.359509831991737,
        "framename": "frame0099",
        "groupname": "20221219_group0073_mode2_199frames"
    },
    {
        "alpha": -2.354596083096197,
        "class": "car",
        "h": 1.653246282063056,
        "l": 4.302611300066194,
        "motion": 0,
        "object_id": "81",
        "occluded": 0,
        "truncated": 0,
        "w": 1.937265526478363,
        "x": 11.90195791268623,
        "y": 34.56322693481002,
        "z": -1.961700710990801,
        "framename": "frame0099",
        "groupname": "20221219_group0073_mode2_199frames"
    },
    {
        "alpha": -2.262311592041691,
        "class": "car",
        "h": 1.603160557789497,
        "l": 4.302611300066195,
        "motion": 0,
        "object_id": "82",
        "occluded": 0,
        "truncated": 0,
        "w": 1.830123814636508,
        "x": 11.2640723762176,
        "y": 40.3962861535365,
        "z": -2.094694003773582,
        "framename": "frame0099",
        "groupname": "20221219_group0073_mode2_199frames"
    },
    {
        "alpha": 2.460675619858047,
        "class": "car",
        "h": 1.578686684497948,
        "l": 4.596094216150608,
        "motion": 0,
        "object_id": "87",
        "occluded": 3,
        "truncated": 3,
        "w": 1.930142772506457,
        "x": 22.24174244004627,
        "y": 20.61566624997065,
        "z": -1.212214958161582,
        "framename": "frame0099",
        "groupname": "20221219_group0073_mode2_199frames"
    },
    {
        "alpha": 1.56173307773013,
        "class": "car",
        "h": 1.735064289183139,
        "l": 4.813774332151674,
        "motion": 0,
        "object_id": "92",
        "occluded": 3,
        "truncated": 3,
        "w": 1.856565385285615,
        "x": 64.69971784388684,
        "y": 5.018809519069711,
        "z": -0.6787990624197711,
        "framename": "frame0099",
        "groupname": "20221219_group0073_mode2_199frames"
    },
    {
        "alpha": 1.703828099600672,
        "class": "car",
        "h": 1.505424602995603,
        "l": 4.360903742732745,
        "motion": 1,
        "object_id": "94",
        "occluded": 2,
        "truncated": 3,
        "w": 1.893734650399861,
        "x": 2.848909950613428,
        "y": 11.20223920695135,
        "z": -1.642660876452202,
        "framename": "frame0099",
        "groupname": "20221219_group0073_mode2_199frames"
    },
    {
        "alpha": 2.315834432628323,
        "class": "car",
        "h": 1.578686684497948,
        "l": 4.596094216150608,
        "motion": 0,
        "object_id": "100",
        "occluded": 3,
        "truncated": 0,
        "w": 1.930142772506457,
        "x": 20.94478025577264,
        "y": 25.91089507928224,
        "z": -1.381904990767428,
        "framename": "frame0099",
        "groupname": "20221219_group0073_mode2_199frames"
    },
    {
        "alpha": 1.727499224396498,
        "class": "car",
        "h": 1.596759519863538,
        "l": 4.222137263395602,
        "motion": 0,
        "object_id": "101",
        "occluded": 3,
        "truncated": 3,
        "w": 1.856565385285615,
        "x": 82.18203129097627,
        "y": 9.9394054846393,
        "z": -0.195996174878267,
        "framename": "frame0099",
        "groupname": "20221219_group0073_mode2_199frames"
    },
    {
        "alpha": 2.476723117900122,
        "class": "car",
        "h": 2.22579809144202,
        "l": 5.244636663113555,
        "motion": 0,
        "object_id": "107",
        "occluded": 3,
        "truncated": 3,
        "w": 2.082987276639816,
        "x": 29.84693262707943,
        "y": 20.47665933028949,
        "z": -0.6635838970337182,
        "framename": "frame0099",
        "groupname": "20221219_group0073_mode2_199frames"
    },
    {
        "alpha": -2.568148103738556,
        "class": "car",
        "h": 1.482954819532956,
        "l": 4.302611300066195,
        "motion": 0,
        "object_id": "110",
        "occluded": 0,
        "truncated": 0,
        "w": 2.104256787100755,
        "x": 13.91360016972096,
        "y": 57.9014742753344,
        "z": -2.809571328721962,
        "framename": "frame0099",
        "groupname": "20221219_group0073_mode2_199frames"
    },
    {
        "alpha": -2.920937827084327,
        "class": "motorcycle",
        "h": 1.351350242799437,
        "l": 1.85300411758113,
        "motion": 0,
        "object_id": "111",
        "occluded": 0,
        "truncated": 0,
        "w": 0.7380435119413864,
        "x": 4.002689964745361,
        "y": 62.48514909514533,
        "z": -3.185484012002031,
        "framename": "frame0099",
        "groupname": "20221219_group0073_mode2_199frames"
    },
    {
        "alpha": 0.1570040612491368,
        "class": "truck",
        "h": 3.1022111694282,
        "l": 7.712965345686408,
        "motion": 0,
        "object_id": "115",
        "occluded": 3,
        "truncated": 3,
        "w": 2.706769149151171,
        "x": -30.50897812650179,
        "y": 29.33643709761357,
        "z": -1.104039038004633,
        "framename": "frame0099",
        "groupname": "20221219_group0073_mode2_199frames"
    },
    {
        "alpha": -3.00412735800967,
        "class": "car",
        "h": 1.389027284277799,
        "l": 4.5407856460539,
        "motion": 0,
        "object_id": "145",
        "occluded": 3,
        "truncated": 3,
        "w": 2.051459444617636,
        "x": 8.751620117591944,
        "y": 57.56967662286741,
        "z": -0.5005512457149305,
        "framename": "frame0099",
        "groupname": "20221219_group0073_mode2_199frames"
    }
]