[
    {
        "alpha": 1.618672803717636,
        "class": "car",
        "h": 1.599476263447896,
        "l": 4.248644613966816,
        "motion": 0,
        "object_id": "1",
        "occluded": 0,
        "truncated": 0,
        "w": 1.971119227879801,
        "x": 0.09231817869727245,
        "y": 7.969321742240279,
        "z": -1.421647612096649,
        "framename": "frame0243",
        "groupname": "20221217_group0003_mode2_291frames"
    },
    {
        "alpha": -0.06218016921003848,
        "class": "car",
        "h": 1.467016877082846,
        "l": 4.656775934041059,
        "motion": 1,
        "object_id": "12",
        "occluded": 3,
        "truncated": 3,
        "w": 2.01773825104076,
        "x": 84.14643554754036,
        "y": 23.89683667908463,
        "z": -1.837682273853794,
        "framename": "frame0243",
        "groupname": "20221217_group0003_mode2_291frames"
    },
    {
        "alpha": 0.004345288124352021,
        "class": "car",
        "h": 1.74478571416019,
        "l": 4.996041085714045,
        "motion": 1,
        "object_id": "14",
        "occluded": 3,
        "truncated": 3,
        "w": 2.118921027218901,
        "x": 34.26724954306972,
        "y": 23.69948685388997,
        "z": -1.872516891670783,
        "framename": "frame0243",
        "groupname": "20221217_group0003_mode2_291frames"
    },
    {
        "alpha": -0.1307170645920075,
        "class": "car",
        "h": 1.519340129752555,
        "l": 4.205727156037272,
        "motion": 1,
        "object_id": "15",
        "occluded": 3,
        "truncated": 3,
        "w": 2.000423049177304,
        "x": 20.04614807744133,
        "y": 23.6009584970643,
        "z": -1.933505765464052,
        "framename": "frame0243",
        "groupname": "20221217_group0003_mode2_291frames"
    },
    {
        "alpha": -3.075054739506679,
        "class": "pedestrian",
        "h": 1.672000999886961,
        "l": 0.8950689350512467,
        "motion": 1,
        "object_id": "16",
        "occluded": 0,
        "truncated": 0,
        "w": 0.7171442846706066,
        "x": -24.18364581714107,
        "y": 47.68600198408928,
        "z": -2.472445398429265,
        "framename": "frame0243",
        "groupname": "20221217_group0003_mode2_291frames"
    },
    {
        "alpha": -3.036065391237474,
        "class": "motorcyclist",
        "h": 1.514389871897913,
        "l": 1.862227082885812,
        "motion": 0,
        "object_id": "19",
        "occluded": 3,
        "truncated": 0,
        "w": 0.7702202974660339,
        "x": 11.81026937024236,
        "y": 55.05607421626329,
        "z": -2.44640093024744,
        "framename": "frame0243",
        "groupname": "20221217_group0003_mode2_291frames"
    },
    {
        "alpha": 0.691004401764458,
        "class": "pedestrian",
        "h": 1.642337265347504,
        "l": 0.9081870934358885,
        "motion": 1,
        "object_id": "24",
        "occluded": 3,
        "truncated": 3,
        "w": 0.8155277930770367,
        "x": 15.67744390148409,
        "y": 15.51685404770273,
        "z": -1.60283425336266,
        "framename": "frame0243",
        "groupname": "20221217_group0003_mode2_291frames"
    },
    {
        "alpha": 3.084788948783187,
        "class": "car",
        "h": 1.458305835723877,
        "l": 4.233437393783423,
        "motion": 0,
        "object_id": "25",
        "occluded": 3,
        "truncated": 3,
        "w": 1.911112668393532,
        "x": 24.83195350394376,
        "y": 35.06223159025339,
        "z": -2.182409975597646,
        "framename": "frame0243",
        "groupname": "20221217_group0003_mode2_291frames"
    },
    {
        "alpha": 3.084788948783187,
        "class": "car",
        "h": 1.537823972822745,
        "l": 4.233437393783423,
        "motion": 0,
        "object_id": "26",
        "occluded": 3,
        "truncated": 3,
        "w": 1.911112668393532,
        "x": 31.35186082725451,
        "y": 34.41786875726015,
        "z": -2.054044310368802,
        "framename": "frame0243",
        "groupname": "20221217_group0003_mode2_291frames"
    },
    {
        "alpha": -3.031258815265657,
        "class": "car",
        "h": 1.537823972822745,
        "l": 4.233437393783423,
        "motion": 0,
        "object_id": "27",
        "occluded": 3,
        "truncated": 3,
        "w": 2.118751348268332,
        "x": 37.88774700255816,
        "y": 33.75581150442294,
        "z": -2.145770044495025,
        "framename": "frame0243",
        "groupname": "20221217_group0003_mode2_291frames"
    },
    {
        "alpha": 3.084641528548556,
        "class": "car",
        "h": 1.458305835723877,
        "l": 4.233437393783429,
        "motion": 0,
        "object_id": "29",
        "occluded": 3,
        "truncated": 3,
        "w": 1.911112668393534,
        "x": 27.00306547866276,
        "y": 40.88562457674512,
        "z": -2.311150338566649,
        "framename": "frame0243",
        "groupname": "20221217_group0003_mode2_291frames"
    },
    {
        "alpha": 3.0852086722277,
        "class": "car",
        "h": 1.569274050501948,
        "l": 4.379654335608661,
        "motion": 0,
        "object_id": "35",
        "occluded": 3,
        "truncated": 3,
        "w": 2.008905793254417,
        "x": 27.1094846961868,
        "y": 44.26890000424809,
        "z": -2.256046610346004,
        "framename": "frame0243",
        "groupname": "20221217_group0003_mode2_291frames"
    },
    {
        "alpha": 3.055804776847352,
        "class": "car",
        "h": 1.983529668826603,
        "l": 4.47585458347013,
        "motion": 0,
        "object_id": "38",
        "occluded": 3,
        "truncated": 3,
        "w": 2.006512554654559,
        "x": 51.24789301205384,
        "y": 42.86426745659757,
        "z": -2.245543526636573,
        "framename": "frame0243",
        "groupname": "20221217_group0003_mode2_291frames"
    },
    {
        "alpha": 0.02855923418345232,
        "class": "car",
        "h": 1.465457200674728,
        "l": 4.828827260819225,
        "motion": 0,
        "object_id": "41",
        "occluded": 3,
        "truncated": 3,
        "w": 1.866103590033795,
        "x": -35.30362769143586,
        "y": 31.9195440778502,
        "z": -2.382064285873938,
        "framename": "frame0243",
        "groupname": "20221217_group0003_mode2_291frames"
    },
    {
        "alpha": -0.05908767826808219,
        "class": "car",
        "h": 1.441892059759355,
        "l": 4.416673212977901,
        "motion": 0,
        "object_id": "42",
        "occluded": 3,
        "truncated": 3,
        "w": 1.92022654634746,
        "x": -36.42268713975889,
        "y": 28.95893144819366,
        "z": -2.41872388318746,
        "framename": "frame0243",
        "groupname": "20221217_group0003_mode2_291frames"
    },
    {
        "alpha": -0.03889667848007104,
        "class": "car",
        "h": 1.441892059759355,
        "l": 4.416673212977901,
        "motion": 0,
        "object_id": "43",
        "occluded": 3,
        "truncated": 3,
        "w": 1.953922173839403,
        "x": -36.05934722288011,
        "y": 25.85765726587971,
        "z": -2.449459666001415,
        "framename": "frame0243",
        "groupname": "20221217_group0003_mode2_291frames"
    },
    {
        "alpha": 0.0007440488723400529,
        "class": "car",
        "h": 1.56795408826433,
        "l": 4.416673212977901,
        "motion": 0,
        "object_id": "44",
        "occluded": 3,
        "truncated": 3,
        "w": 1.953922173839402,
        "x": -34.91439872593675,
        "y": 22.38429083269844,
        "z": -2.297460197980471,
        "framename": "frame0243",
        "groupname": "20221217_group0003_mode2_291frames"
    },
    {
        "alpha": -0.01181627100139593,
        "class": "car",
        "h": 1.56795408826433,
        "l": 4.4166732129779,
        "motion": 0,
        "object_id": "46",
        "occluded": 3,
        "truncated": 3,
        "w": 1.953922173839403,
        "x": -43.76085492473838,
        "y": 32.39632478032753,
        "z": -2.282836440666239,
        "framename": "frame0243",
        "groupname": "20221217_group0003_mode2_291frames"
    },
    {
        "alpha": 0.01908205070403025,
        "class": "car",
        "h": 1.454539687666549,
        "l": 4.5856649242562,
        "motion": 0,
        "object_id": "47",
        "occluded": 3,
        "truncated": 3,
        "w": 2.115946847908588,
        "x": -53.59924466114507,
        "y": 26.21230381838622,
        "z": -2.766557401699347,
        "framename": "frame0243",
        "groupname": "20221217_group0003_mode2_291frames"
    },
    {
        "alpha": -0.01622691507480816,
        "class": "car",
        "h": 1.454539687666549,
        "l": 4.423670779078392,
        "motion": 0,
        "object_id": "48",
        "occluded": 3,
        "truncated": 3,
        "w": 1.953922173839403,
        "x": -61.97656218220094,
        "y": 26.09878459037686,
        "z": -2.914882135028956,
        "framename": "frame0243",
        "groupname": "20221217_group0003_mode2_291frames"
    },
    {
        "alpha": 0.008191093723196766,
        "class": "car",
        "h": 1.77921277236955,
        "l": 4.734817697948079,
        "motion": 0,
        "object_id": "49",
        "occluded": 3,
        "truncated": 3,
        "w": 1.953922173839403,
        "x": -69.6384155358431,
        "y": 26.13957273628671,
        "z": -2.747282751794558,
        "framename": "frame0243",
        "groupname": "20221217_group0003_mode2_291frames"
    },
    {
        "alpha": 0.1102812672869163,
        "class": "motorcyclist",
        "h": 1.603322028533947,
        "l": 1.935440502083157,
        "motion": 0,
        "object_id": "57",
        "occluded": 3,
        "truncated": 3,
        "w": 0.8602956474748317,
        "x": -20.31839415664628,
        "y": 10.29307847783894,
        "z": -1.873634695331152,
        "framename": "frame0243",
        "groupname": "20221217_group0003_mode2_291frames"
    },
    {
        "alpha": 0.1027661128102371,
        "class": "motorcyclist",
        "h": 1.603322028533947,
        "l": 1.881096452191802,
        "motion": 0,
        "object_id": "58",
        "occluded": 3,
        "truncated": 3,
        "w": 0.7350451743597026,
        "x": -19.65288322574797,
        "y": 11.53287868307257,
        "z": -1.880050616132298,
        "framename": "frame0243",
        "groupname": "20221217_group0003_mode2_291frames"
    },
    {
        "alpha": -0.2849167302908435,
        "class": "motorcyclist",
        "h": 1.603322028533947,
        "l": 1.772457357183172,
        "motion": 0,
        "object_id": "59",
        "occluded": 3,
        "truncated": 3,
        "w": 0.9731757034921702,
        "x": -19.87502348186307,
        "y": 12.94117810104671,
        "z": -1.885744288740669,
        "framename": "frame0243",
        "groupname": "20221217_group0003_mode2_291frames"
    },
    {
        "alpha": -0.3439678297574602,
        "class": "motorcyclist",
        "h": 1.603322028533946,
        "l": 1.772457357183172,
        "motion": 0,
        "object_id": "60",
        "occluded": 3,
        "truncated": 3,
        "w": 0.8340085111420269,
        "x": -19.3339207116078,
        "y": 14.1160271124728,
        "z": -1.918421748984016,
        "framename": "frame0243",
        "groupname": "20221217_group0003_mode2_291frames"
    },
    {
        "alpha": -0.646799034604403,
        "class": "motorcyclist",
        "h": 1.603322028533946,
        "l": 1.772457357183172,
        "motion": 0,
        "object_id": "61",
        "occluded": 3,
        "truncated": 3,
        "w": 0.8556567410631604,
        "x": -20.06401594061922,
        "y": 15.80491246732869,
        "z": -1.921138421549119,
        "framename": "frame0243",
        "groupname": "20221217_group0003_mode2_291frames"
    },
    {
        "alpha": -0.8060689244506565,
        "class": "motorcyclist",
        "h": 1.603322028533946,
        "l": 1.772457357183172,
        "motion": 0,
        "object_id": "62",
        "occluded": 3,
        "truncated": 3,
        "w": 0.9136430712090534,
        "x": -21.31109215659192,
        "y": 15.39881475167343,
        "z": -1.978113337758519,
        "framename": "frame0243",
        "groupname": "20221217_group0003_mode2_291frames"
    },
    {
        "alpha": 3.108672225521022,
        "class": "pedestrian",
        "h": 1.632272543786447,
        "l": 0.8084883562029417,
        "motion": 1,
        "object_id": "63",
        "occluded": 3,
        "truncated": 3,
        "w": 0.9569154981150556,
        "x": -22.52072645717666,
        "y": 17.74981705170286,
        "z": -1.998581605241906,
        "framename": "frame0243",
        "groupname": "20221217_group0003_mode2_291frames"
    },
    {
        "alpha": 2.064747182379223,
        "class": "pedestrian",
        "h": 1.643421229387251,
        "l": 0.82741060781547,
        "motion": 1,
        "object_id": "64",
        "occluded": 0,
        "truncated": 0,
        "w": 0.9017489265438949,
        "x": -26.97441080079694,
        "y": 44.13198008493586,
        "z": -2.481192520102627,
        "framename": "frame0243",
        "groupname": "20221217_group0003_mode2_291frames"
    },
    {
        "alpha": 2.143877942486109,
        "class": "pedestrian",
        "h": 1.763171453629581,
        "l": 0.87627377797549,
        "motion": 1,
        "object_id": "65",
        "occluded": 3,
        "truncated": 3,
        "w": 0.9894630621257119,
        "x": -28.73941095247289,
        "y": 15.91571572648769,
        "z": -2.000261474951009,
        "framename": "frame0243",
        "groupname": "20221217_group0003_mode2_291frames"
    },
    {
        "alpha": 3.093725466041185,
        "class": "motorcyclist",
        "h": 1.565508517362821,
        "l": 1.86222708288581,
        "motion": 0,
        "object_id": "66",
        "occluded": 3,
        "truncated": 0,
        "w": 0.8907142474904608,
        "x": 11.53771355120855,
        "y": 57.7450218067459,
        "z": -2.608096630563586,
        "framename": "frame0243",
        "groupname": "20221217_group0003_mode2_291frames"
    },
    {
        "alpha": 0.005034576816332353,
        "class": "car",
        "h": 1.460444369140731,
        "l": 4.00927624141381,
        "motion": 0,
        "object_id": "72",
        "occluded": 3,
        "truncated": 3,
        "w": 1.953922173839402,
        "x": -40.9814820214951,
        "y": 22.99461711501571,
        "z": -2.507642064113409,
        "framename": "frame0243",
        "groupname": "20221217_group0003_mode2_291frames"
    },
    {
        "alpha": -0.1031943511819269,
        "class": "motorcyclist",
        "h": 1.535671310030404,
        "l": 1.814040696447406,
        "motion": 0,
        "object_id": "73",
        "occluded": 3,
        "truncated": 3,
        "w": 0.9462445255437884,
        "x": -21.84937276873301,
        "y": 12.39894472786215,
        "z": -1.953513723003671,
        "framename": "frame0243",
        "groupname": "20221217_group0003_mode2_291frames"
    },
    {
        "alpha": 0.05421574290233016,
        "class": "car",
        "h": 1.569010419515764,
        "l": 4.548545042425704,
        "motion": 0,
        "object_id": "79",
        "occluded": 3,
        "truncated": 3,
        "w": 2.086328116414573,
        "x": -91.8700463236586,
        "y": 29.72452097064921,
        "z": -3.295718180695319,
        "framename": "frame0243",
        "groupname": "20221217_group0003_mode2_291frames"
    },
    {
        "alpha": 1.522324861850744,
        "class": "car",
        "h": 1.467016877082845,
        "l": 4.468757880529589,
        "motion": 1,
        "object_id": "81",
        "occluded": 3,
        "truncated": 0,
        "w": 1.88149016441023,
        "x": -0.8691878740271954,
        "y": 100.4033037403436,
        "z": -3.491416836265638,
        "framename": "frame0243",
        "groupname": "20221217_group0003_mode2_291frames"
    },
    {
        "alpha": 1.531542038794298,
        "class": "car",
        "h": 1.467016877082845,
        "l": 4.755742331572773,
        "motion": 0,
        "object_id": "85",
        "occluded": 3,
        "truncated": 3,
        "w": 1.881490164410228,
        "x": 6.758778638236642,
        "y": 4.203804577097045,
        "z": -1.404570205556281,
        "framename": "frame0243",
        "groupname": "20221217_group0003_mode2_291frames"
    },
    {
        "alpha": 1.624429711296181,
        "class": "car",
        "h": 1.467016877082845,
        "l": 4.755742331572772,
        "motion": 0,
        "object_id": "87",
        "occluded": 3,
        "truncated": 3,
        "w": 1.881490164410228,
        "x": 9.511127847411457,
        "y": 5.07321754648984,
        "z": -1.453234782976252,
        "framename": "frame0243",
        "groupname": "20221217_group0003_mode2_291frames"
    },
    {
        "alpha": 1.593470959060302,
        "class": "car",
        "h": 1.652766019075552,
        "l": 3.544349789477602,
        "motion": 0,
        "object_id": "88",
        "occluded": 3,
        "truncated": 3,
        "w": 1.847916963837227,
        "x": 3.538762728340661,
        "y": 3.643813208232436,
        "z": -1.375313560561405,
        "framename": "frame0243",
        "groupname": "20221217_group0003_mode2_291frames"
    },
    {
        "alpha": -0.08171417849823617,
        "class": "car",
        "h": 1.462023664263235,
        "l": 4.627700484466564,
        "motion": 1,
        "object_id": "93",
        "occluded": 3,
        "truncated": 3,
        "w": 1.993020397712679,
        "x": 47.23985031481669,
        "y": 23.09805211637592,
        "z": -1.937901111543823,
        "framename": "frame0243",
        "groupname": "20221217_group0003_mode2_291frames"
    },
    {
        "alpha": 1.641600859999913,
        "class": "motorcyclist",
        "h": 1.686291408364154,
        "l": 1.665492699471026,
        "motion": 0,
        "object_id": "96",
        "occluded": 3,
        "truncated": 3,
        "w": 0.8126553344414538,
        "x": 21.25978344929766,
        "y": 14.19825153809518,
        "z": -1.593975936068148,
        "framename": "frame0243",
        "groupname": "20221217_group0003_mode2_291frames"
    },
    {
        "alpha": -0.3368140349531894,
        "class": "car",
        "h": 1.519340129752555,
        "l": 5.028826118304659,
        "motion": 1,
        "object_id": "97",
        "occluded": 0,
        "truncated": 0,
        "w": 2.113984336753746,
        "x": 10.27914773879301,
        "y": 25.6893557245622,
        "z": -1.92552926503576,
        "framename": "frame0243",
        "groupname": "20221217_group0003_mode2_291frames"
    },
    {
        "alpha": -0.9499780438531654,
        "class": "car",
        "h": 1.428726915653507,
        "l": 4.526885154364892,
        "motion": 1,
        "object_id": "98",
        "occluded": 0,
        "truncated": 0,
        "w": 2.047763734817111,
        "x": -3.003784935094654,
        "y": 33.47684691363356,
        "z": -2.108190585920732,
        "framename": "frame0243",
        "groupname": "20221217_group0003_mode2_291frames"
    },
    {
        "alpha": -1.641396967075778,
        "class": "motorcyclist",
        "h": 1.490221397315043,
        "l": 1.709678296958522,
        "motion": 1,
        "object_id": "101",
        "occluded": 3,
        "truncated": 3,
        "w": 0.818250086270705,
        "x": -28.14537450698145,
        "y": 26.22717019068239,
        "z": -2.231205859319802,
        "framename": "frame0243",
        "groupname": "20221217_group0003_mode2_291frames"
    },
    {
        "alpha": -0.07158982798337674,
        "class": "car",
        "h": 1.519340129752555,
        "l": 4.69945178032165,
        "motion": 1,
        "object_id": "103",
        "occluded": 3,
        "truncated": 3,
        "w": 2.038887356259647,
        "x": 24.5335636964607,
        "y": 26.54962349098326,
        "z": -1.975812941715293,
        "framename": "frame0243",
        "groupname": "20221217_group0003_mode2_291frames"
    },
    {
        "alpha": 0.6062262287467272,
        "class": "pedestrian",
        "h": 1.885329484608925,
        "l": 0.8834120931598959,
        "motion": 1,
        "object_id": "105",
        "occluded": 3,
        "truncated": 3,
        "w": 0.6678031064915757,
        "x": 32.78729734667563,
        "y": 2.962817399915601,
        "z": -1.486109175773404,
        "framename": "frame0243",
        "groupname": "20221217_group0003_mode2_291frames"
    },
    {
        "alpha": 1.771002141151744,
        "class": "motorcyclist",
        "h": 1.633946356214589,
        "l": 1.918537817462754,
        "motion": 0,
        "object_id": "106",
        "occluded": 3,
        "truncated": 3,
        "w": 1.016473100834143,
        "x": 19.596875285723,
        "y": 17.6141056825019,
        "z": -1.672146937127701,
        "framename": "frame0243",
        "groupname": "20221217_group0003_mode2_291frames"
    },
    {
        "alpha": -1.438399003367708,
        "class": "car",
        "h": 1.519340129752555,
        "l": 4.444966968403969,
        "motion": 1,
        "object_id": "108",
        "occluded": 0,
        "truncated": 0,
        "w": 2.000423049177304,
        "x": -7.167625230464898,
        "y": 44.23968766921778,
        "z": -2.321009435928504,
        "framename": "frame0243",
        "groupname": "20221217_group0003_mode2_291frames"
    },
    {
        "alpha": 1.980784657737346,
        "class": "motorcyclist",
        "h": 1.633946356214589,
        "l": 1.868898940818259,
        "motion": 1,
        "object_id": "109",
        "occluded": 3,
        "truncated": 3,
        "w": 0.9219228596065356,
        "x": 18.31891988763177,
        "y": 16.86658233062037,
        "z": -1.666588156399463,
        "framename": "frame0243",
        "groupname": "20221217_group0003_mode2_291frames"
    },
    {
        "alpha": -0.2982886877257782,
        "class": "car",
        "h": 1.519340129752555,
        "l": 4.444966968403969,
        "motion": 1,
        "object_id": "110",
        "occluded": 3,
        "truncated": 0,
        "w": 2.000423049177304,
        "x": 10.27298257790945,
        "y": 30.5086815187388,
        "z": -2.030039631755797,
        "framename": "frame0243",
        "groupname": "20221217_group0003_mode2_291frames"
    },
    {
        "alpha": 1.6797665091589,
        "class": "motorcyclist",
        "h": 1.63394635621459,
        "l": 1.899923238721068,
        "motion": 1,
        "object_id": "111",
        "occluded": 3,
        "truncated": 3,
        "w": 0.9219228596065359,
        "x": 22.39732371798041,
        "y": 14.30703721971087,
        "z": -1.6372625502597,
        "framename": "frame0243",
        "groupname": "20221217_group0003_mode2_291frames"
    },
    {
        "alpha": -1.53275069930697,
        "class": "car",
        "h": 1.519340129752555,
        "l": 4.444966968403969,
        "motion": 1,
        "object_id": "113",
        "occluded": 0,
        "truncated": 0,
        "w": 2.128637406118447,
        "x": -8.60915421942887,
        "y": 58.34161268848218,
        "z": -2.584004769834598,
        "framename": "frame0243",
        "groupname": "20221217_group0003_mode2_291frames"
    },
    {
        "alpha": -1.135266251913043,
        "class": "car",
        "h": 1.403947208505525,
        "l": 4.816352995302171,
        "motion": 1,
        "object_id": "115",
        "occluded": 0,
        "truncated": 0,
        "w": 2.000423049177304,
        "x": -1.807018691081464,
        "y": 43.12664233725286,
        "z": -2.320676555987445,
        "framename": "frame0243",
        "groupname": "20221217_group0003_mode2_291frames"
    },
    {
        "alpha": -1.532648990283337,
        "class": "car",
        "h": 1.420431911540815,
        "l": 4.635830305135193,
        "motion": 1,
        "object_id": "116",
        "occluded": 0,
        "truncated": 0,
        "w": 2.07735166334199,
        "x": -13.24152683416277,
        "y": 39.56035647026626,
        "z": -2.297058544483998,
        "framename": "frame0243",
        "groupname": "20221217_group0003_mode2_291frames"
    },
    {
        "alpha": 2.380812390011547,
        "class": "car",
        "h": 1.462126543820391,
        "l": 4.379654335608659,
        "motion": 1,
        "object_id": "117",
        "occluded": 0,
        "truncated": 0,
        "w": 2.008905793254416,
        "x": 17.36634490048784,
        "y": 60.24020590972989,
        "z": -2.801509074008635,
        "framename": "frame0243",
        "groupname": "20221217_group0003_mode2_291frames"
    },
    {
        "alpha": 1.03947260673849,
        "class": "car",
        "h": 1.53350169779509,
        "l": 4.703385535261877,
        "motion": 1,
        "object_id": "119",
        "occluded": 3,
        "truncated": 3,
        "w": 1.903674637434388,
        "x": 19.90237137620504,
        "y": -0.4423248423174787,
        "z": -1.545969114004026,
        "framename": "frame0243",
        "groupname": "20221217_group0003_mode2_291frames"
    },
    {
        "alpha": -1.532681503962756,
        "class": "car",
        "h": 1.519340129752555,
        "l": 4.444966968403969,
        "motion": 1,
        "object_id": "120",
        "occluded": 3,
        "truncated": 0,
        "w": 2.07735166334199,
        "x": -25.39498365062922,
        "y": 89.92319167628976,
        "z": -3.955106230453123,
        "framename": "frame0243",
        "groupname": "20221217_group0003_mode2_291frames"
    }
]