[
    {
        "alpha": 1.616101701142993,
        "class": "car",
        "h": 1.449275585374749,
        "l": 4.168996810913086,
        "motion": 1,
        "object_id": "1",
        "occluded": 0,
        "truncated": 0,
        "w": 1.980577075253961,
        "x": -3.729944934624931,
        "y": 15.49535148894238,
        "z": -1.290700661440003,
        "framename": "frame0059",
        "groupname": "20221224_group0058_mode2_88frames"
    },
    {
        "alpha": 1.628370399956209,
        "class": "car",
        "h": 1.499979104396606,
        "l": 4.933312892913818,
        "motion": 1,
        "object_id": "2",
        "occluded": 0,
        "truncated": 0,
        "w": 2.041720037158327,
        "x": -5.242865311647196,
        "y": 33.46376929576812,
        "z": -1.174441635083172,
        "framename": "frame0059",
        "groupname": "20221224_group0058_mode2_88frames"
    },
    {
        "alpha": 1.628370399956211,
        "class": "car",
        "h": 1.499979104396606,
        "l": 4.588124818774075,
        "motion": 1,
        "object_id": "3",
        "occluded": 0,
        "truncated": 0,
        "w": 2.045218530696278,
        "x": -0.8122238050451592,
        "y": 14.55594075134736,
        "z": -1.287882638128591,
        "framename": "frame0059",
        "groupname": "20221224_group0058_mode2_88frames"
    },
    {
        "alpha": 1.613776999045658,
        "class": "car",
        "h": 1.499979104396606,
        "l": 4.588124818774077,
        "motion": 1,
        "object_id": "4",
        "occluded": 3,
        "truncated": 0,
        "w": 2.071457232230912,
        "x": -1.574772342620637,
        "y": 30.64513200562184,
        "z": -1.18196009165573,
        "framename": "frame0059",
        "groupname": "20221224_group0058_mode2_88frames"
    },
    {
        "alpha": 1.629272346577377,
        "class": "car",
        "h": 1.464994169017093,
        "l": 4.572632203286947,
        "motion": 1,
        "object_id": "5",
        "occluded": 2,
        "truncated": 2,
        "w": 2.028301873226102,
        "x": 2.938547869157395,
        "y": 5.102992192870032,
        "z": -1.360596039483635,
        "framename": "frame0059",
        "groupname": "20221224_group0058_mode2_88frames"
    },
    {
        "alpha": 1.629272346577377,
        "class": "car",
        "h": 1.587441442845388,
        "l": 4.588124818774077,
        "motion": 1,
        "object_id": "6",
        "occluded": 0,
        "truncated": 0,
        "w": 2.071457232230912,
        "x": 1.553785032968557,
        "y": 31.34658758155921,
        "z": -1.162328889072055,
        "framename": "frame0059",
        "groupname": "20221224_group0058_mode2_88frames"
    },
    {
        "alpha": 1.638096207735739,
        "class": "car",
        "h": 1.631000117318936,
        "l": 4.588124818774076,
        "motion": 1,
        "object_id": "7",
        "occluded": 3,
        "truncated": 0,
        "w": 2.071457232230912,
        "x": 1.279156534684452,
        "y": 48.16068468825784,
        "z": -1.027245911990265,
        "framename": "frame0059",
        "groupname": "20221224_group0058_mode2_88frames"
    },
    {
        "alpha": 1.629272346577377,
        "class": "car",
        "h": 1.476366822937839,
        "l": 4.588124818774077,
        "motion": 1,
        "object_id": "8",
        "occluded": 3,
        "truncated": 0,
        "w": 2.036932945027064,
        "x": -1.965806545816264,
        "y": 46.12433067476321,
        "z": -1.143828269067549,
        "framename": "frame0059",
        "groupname": "20221224_group0058_mode2_88frames"
    },
    {
        "alpha": 1.602125005299572,
        "class": "car",
        "h": 1.68974850452659,
        "l": 4.588124818774076,
        "motion": 1,
        "object_id": "9",
        "occluded": 3,
        "truncated": 3,
        "w": 2.036932945027063,
        "x": -6.208795896711629,
        "y": 5.392101500957033,
        "z": -1.245778975194984,
        "framename": "frame0059",
        "groupname": "20221224_group0058_mode2_88frames"
    },
    {
        "alpha": 1.59300900752128,
        "class": "car",
        "h": 1.681260391899569,
        "l": 4.588124818774077,
        "motion": 1,
        "object_id": "10",
        "occluded": 0,
        "truncated": 0,
        "w": 2.132731257955814,
        "x": -6.360542399217301,
        "y": 62.16272801345083,
        "z": -0.8694697081394327,
        "framename": "frame0059",
        "groupname": "20221224_group0058_mode2_88frames"
    },
    {
        "alpha": 0.05640244852165156,
        "class": "special_vehicle",
        "h": 3.473782462980075,
        "l": 7.747372696797052,
        "motion": 0,
        "object_id": "12",
        "occluded": 3,
        "truncated": 3,
        "w": 3.182970858176317,
        "x": -37.06319602128957,
        "y": 21.73821305031394,
        "z": -1.01699568360518,
        "framename": "frame0059",
        "groupname": "20221224_group0058_mode2_88frames"
    },
    {
        "alpha": 0.04745915256211457,
        "class": "special_vehicle",
        "h": 3.413016588992085,
        "l": 7.824846423765023,
        "motion": 0,
        "object_id": "13",
        "occluded": 3,
        "truncated": 3,
        "w": 3.182970858176318,
        "x": -50.34900259519379,
        "y": 20.87667694250842,
        "z": -1.380255441051249,
        "framename": "frame0059",
        "groupname": "20221224_group0058_mode2_88frames"
    },
    {
        "alpha": 0.04159255685965426,
        "class": "truck",
        "h": 3.939041700736466,
        "l": 11.3989207381279,
        "motion": 0,
        "object_id": "14",
        "occluded": 3,
        "truncated": 3,
        "w": 3.270103774437354,
        "x": -60.39578934979913,
        "y": 24.34060620232011,
        "z": -1.193092796567929,
        "framename": "frame0059",
        "groupname": "20221224_group0058_mode2_88frames"
    },
    {
        "alpha": 0.05014004459053497,
        "class": "car",
        "h": 1.798304462518178,
        "l": 5.164234550193717,
        "motion": 0,
        "object_id": "16",
        "occluded": 3,
        "truncated": 3,
        "w": 1.908152706989274,
        "x": -36.1264966756997,
        "y": 30.90066370305372,
        "z": -1.744655870606517,
        "framename": "frame0059",
        "groupname": "20221224_group0058_mode2_88frames"
    },
    {
        "alpha": 0.03793784432020206,
        "class": "car",
        "h": 1.642397522926331,
        "l": 4.478114138352565,
        "motion": 0,
        "object_id": "22",
        "occluded": 3,
        "truncated": 3,
        "w": 1.908152706989274,
        "x": 34.03880207547154,
        "y": 10.43635013144362,
        "z": -1.595512836728731,
        "framename": "frame0059",
        "groupname": "20221224_group0058_mode2_88frames"
    },
    {
        "alpha": -0.0307003666483623,
        "class": "car",
        "h": 1.43171096021858,
        "l": 4.478114138352565,
        "motion": 0,
        "object_id": "23",
        "occluded": 3,
        "truncated": 3,
        "w": 1.908152706989274,
        "x": 43.39936777832861,
        "y": 10.67587895332932,
        "z": -1.676647786620492,
        "framename": "frame0059",
        "groupname": "20221224_group0058_mode2_88frames"
    },
    {
        "alpha": 0.01235789760970719,
        "class": "car",
        "h": 1.43171096021858,
        "l": 4.478114138352565,
        "motion": 0,
        "object_id": "24",
        "occluded": 3,
        "truncated": 3,
        "w": 1.908152706989274,
        "x": 50.16545210743954,
        "y": 10.76748731659351,
        "z": -1.626675415266445,
        "framename": "frame0059",
        "groupname": "20221224_group0058_mode2_88frames"
    },
    {
        "alpha": 0.01235789760970723,
        "class": "car",
        "h": 1.523540817725311,
        "l": 4.478114138352565,
        "motion": 0,
        "object_id": "25",
        "occluded": 3,
        "truncated": 3,
        "w": 2.068057865700969,
        "x": 39.38319967236536,
        "y": 18.34480435865913,
        "z": -1.485515455349905,
        "framename": "frame0059",
        "groupname": "20221224_group0058_mode2_88frames"
    },
    {
        "alpha": -0.02725395877812817,
        "class": "car",
        "h": 1.43171096021858,
        "l": 4.373668327545507,
        "motion": 0,
        "object_id": "26",
        "occluded": 3,
        "truncated": 3,
        "w": 1.908152706989274,
        "x": 52.43205591807595,
        "y": 18.73250956555965,
        "z": -1.400471864932601,
        "framename": "frame0059",
        "groupname": "20221224_group0058_mode2_88frames"
    },
    {
        "alpha": 0.02498285919726708,
        "class": "car",
        "h": 1.43171096021858,
        "l": 4.373668327545507,
        "motion": 0,
        "object_id": "27",
        "occluded": 3,
        "truncated": 3,
        "w": 1.908152706989274,
        "x": 65.10852069218659,
        "y": 19.04874464078927,
        "z": -1.295320391688475,
        "framename": "frame0059",
        "groupname": "20221224_group0058_mode2_88frames"
    },
    {
        "alpha": -1.557410408878197,
        "class": "car",
        "h": 1.672385453037607,
        "l": 4.678088050514745,
        "motion": 1,
        "object_id": "34",
        "occluded": 3,
        "truncated": 3,
        "w": 2.120239589188475,
        "x": -11.71657201851222,
        "y": 3.701805932232498,
        "z": -1.308027766040834,
        "framename": "frame0059",
        "groupname": "20221224_group0058_mode2_88frames"
    },
    {
        "alpha": -1.547564372498903,
        "class": "car",
        "h": 1.510541721628039,
        "l": 4.678088050514743,
        "motion": 1,
        "object_id": "35",
        "occluded": 1,
        "truncated": 0,
        "w": 2.120239589188475,
        "x": -12.53252631524209,
        "y": 38.70432131596173,
        "z": -1.229291446239937,
        "framename": "frame0059",
        "groupname": "20221224_group0058_mode2_88frames"
    },
    {
        "alpha": -1.547564372498902,
        "class": "car",
        "h": 1.672385453037607,
        "l": 4.678088050514742,
        "motion": 1,
        "object_id": "36",
        "occluded": 3,
        "truncated": 0,
        "w": 2.208003257277912,
        "x": -11.49786850280202,
        "y": 68.65625968160309,
        "z": -0.8527955310105697,
        "framename": "frame0059",
        "groupname": "20221224_group0058_mode2_88frames"
    },
    {
        "alpha": -1.547564372498901,
        "class": "car",
        "h": 1.746852253491366,
        "l": 4.678088050514743,
        "motion": 1,
        "object_id": "38",
        "occluded": 3,
        "truncated": 3,
        "w": 2.120239589188475,
        "x": -18.65835219507117,
        "y": 24.98980767140706,
        "z": -1.2916446991517,
        "framename": "frame0059",
        "groupname": "20221224_group0058_mode2_88frames"
    },
    {
        "alpha": 3.118071143990436,
        "class": "car",
        "h": 1.43171096021858,
        "l": 4.446562799671269,
        "motion": 0,
        "object_id": "43",
        "occluded": 3,
        "truncated": 3,
        "w": 1.908152706989275,
        "x": 74.84533307450849,
        "y": 74.64213625862935,
        "z": -0.4857378606459427,
        "framename": "frame0059",
        "groupname": "20221224_group0058_mode2_88frames"
    },
    {
        "alpha": -3.10329231543727,
        "class": "car",
        "h": 1.885157455942048,
        "l": 4.373668327545506,
        "motion": 0,
        "object_id": "44",
        "occluded": 3,
        "truncated": 3,
        "w": 1.908152706989273,
        "x": 67.33238212331526,
        "y": 74.35915807887291,
        "z": -0.2305958142369761,
        "framename": "frame0059",
        "groupname": "20221224_group0058_mode2_88frames"
    },
    {
        "alpha": -2.449433109101621,
        "class": "car",
        "h": 1.506844479996814,
        "l": 4.37366832754551,
        "motion": 0,
        "object_id": "45",
        "occluded": 3,
        "truncated": 3,
        "w": 1.908152706989275,
        "x": 55.96808335342501,
        "y": 73.55856466095142,
        "z": -0.753989822334648,
        "framename": "frame0059",
        "groupname": "20221224_group0058_mode2_88frames"
    },
    {
        "alpha": -3.099161620456711,
        "class": "car",
        "h": 1.43171096021858,
        "l": 4.373668327545509,
        "motion": 0,
        "object_id": "47",
        "occluded": 3,
        "truncated": 3,
        "w": 1.908152706989274,
        "x": 87.05116467113915,
        "y": 74.53921408497727,
        "z": -0.2588268646747346,
        "framename": "frame0059",
        "groupname": "20221224_group0058_mode2_88frames"
    },
    {
        "alpha": 0.005327697897191407,
        "class": "car",
        "h": 1.43171096021858,
        "l": 4.373668327545507,
        "motion": 0,
        "object_id": "48",
        "occluded": 3,
        "truncated": 3,
        "w": 1.908152706989274,
        "x": 93.81996287317604,
        "y": 74.42642644377412,
        "z": -0.2372620804370276,
        "framename": "frame0059",
        "groupname": "20221224_group0058_mode2_88frames"
    },
    {
        "alpha": -0.03511957976220106,
        "class": "special_vehicle",
        "h": 4.26373882482394,
        "l": 7.747372696797051,
        "motion": 0,
        "object_id": "50",
        "occluded": 3,
        "truncated": 3,
        "w": 3.421798054898281,
        "x": 99.20479047605514,
        "y": 69.31658405174981,
        "z": 0.705577383451808,
        "framename": "frame0059",
        "groupname": "20221224_group0058_mode2_88frames"
    },
    {
        "alpha": 0.04820151992325396,
        "class": "car",
        "h": 1.754376197128187,
        "l": 4.55691085411374,
        "motion": 0,
        "object_id": "51",
        "occluded": 3,
        "truncated": 0,
        "w": 1.908152706989274,
        "x": 28.95429375524278,
        "y": 80.02179794668619,
        "z": -0.8642083886511659,
        "framename": "frame0059",
        "groupname": "20221224_group0058_mode2_88frames"
    },
    {
        "alpha": 0.02498285919726702,
        "class": "car",
        "h": 1.565281662046552,
        "l": 4.373668327545507,
        "motion": 0,
        "object_id": "70",
        "occluded": 3,
        "truncated": 3,
        "w": 1.908152706989274,
        "x": 59.36920944732555,
        "y": 19.00091090190609,
        "z": -1.380144968334814,
        "framename": "frame0059",
        "groupname": "20221224_group0058_mode2_88frames"
    },
    {
        "alpha": -3.134503933097617,
        "class": "car",
        "h": 1.49940691667593,
        "l": 4.373668327545512,
        "motion": 0,
        "object_id": "75",
        "occluded": 3,
        "truncated": 3,
        "w": 1.908152706989275,
        "x": 81.1425672934115,
        "y": 74.5376010386913,
        "z": -0.1419270781619182,
        "framename": "frame0059",
        "groupname": "20221224_group0058_mode2_88frames"
    },
    {
        "alpha": -1.58223038903383,
        "class": "car",
        "h": 1.638638457839101,
        "l": 4.373668327545509,
        "motion": 0,
        "object_id": "77",
        "occluded": 3,
        "truncated": 3,
        "w": 1.908152706989274,
        "x": 66.60615441641727,
        "y": 80.82575277212383,
        "z": -0.2080337867837098,
        "framename": "frame0059",
        "groupname": "20221224_group0058_mode2_88frames"
    },
    {
        "alpha": -1.508223599275893,
        "class": "car",
        "h": 1.755645114726572,
        "l": 5.039493284221175,
        "motion": 1,
        "object_id": "86",
        "occluded": 3,
        "truncated": 3,
        "w": 2.218949739591689,
        "x": -17.32297369931531,
        "y": 1.635944128479871,
        "z": -1.389476893716912,
        "framename": "frame0059",
        "groupname": "20221224_group0058_mode2_88frames"
    },
    {
        "alpha": 1.577042256180523,
        "class": "car",
        "h": 1.566054384369157,
        "l": 4.478114138352565,
        "motion": 0,
        "object_id": "88",
        "occluded": 3,
        "truncated": 3,
        "w": 1.908152706989274,
        "x": -77.40693814225507,
        "y": 68.31415615358644,
        "z": -1.575340706763204,
        "framename": "frame0059",
        "groupname": "20221224_group0058_mode2_88frames"
    },
    {
        "alpha": 0.01235789760970723,
        "class": "car",
        "h": 1.43171096021858,
        "l": 4.478114138352565,
        "motion": 0,
        "object_id": "95",
        "occluded": 3,
        "truncated": 3,
        "w": 1.908152706989274,
        "x": 56.26322534276823,
        "y": 10.90495226059797,
        "z": -1.422836997801415,
        "framename": "frame0059",
        "groupname": "20221224_group0058_mode2_88frames"
    },
    {
        "alpha": 1.638096207735736,
        "class": "pedestrian",
        "h": 1.585790545022915,
        "l": 0.8066707714211039,
        "motion": 1,
        "object_id": "114",
        "occluded": 0,
        "truncated": 0,
        "w": 0.645058403056994,
        "x": 10.10628513938721,
        "y": 29.34309760858134,
        "z": -1.264371845972714,
        "framename": "frame0059",
        "groupname": "20221224_group0058_mode2_88frames"
    },
    {
        "alpha": -1.547564372498891,
        "class": "car",
        "h": 1.481796680609229,
        "l": 4.678088050514742,
        "motion": 1,
        "object_id": "118",
        "occluded": 0,
        "truncated": 0,
        "w": 2.120239589188475,
        "x": -15.88098975720661,
        "y": 40.83999525164987,
        "z": -1.282115084252017,
        "framename": "frame0059",
        "groupname": "20221224_group0058_mode2_88frames"
    },
    {
        "alpha": -1.533470158667709,
        "class": "bus",
        "h": 3.665179507472341,
        "l": 12.21220049606423,
        "motion": 1,
        "object_id": "120",
        "occluded": 1,
        "truncated": 0,
        "w": 3.256154947947868,
        "x": -17.91764752214136,
        "y": 77.67398665315015,
        "z": 0.08295130490668728,
        "framename": "frame0059",
        "groupname": "20221224_group0058_mode2_88frames"
    },
    {
        "alpha": 0.01235789760970726,
        "class": "car",
        "h": 1.43171096021858,
        "l": 4.478114138352565,
        "motion": 0,
        "object_id": "126",
        "occluded": 3,
        "truncated": 3,
        "w": 1.908152706989274,
        "x": 61.9328068880499,
        "y": 11.07562966267949,
        "z": -1.445561369887913,
        "framename": "frame0059",
        "groupname": "20221224_group0058_mode2_88frames"
    },
    {
        "alpha": -0.04934144400997227,
        "class": "car",
        "h": 1.861425653716572,
        "l": 4.373668327545507,
        "motion": 0,
        "object_id": "128",
        "occluded": 3,
        "truncated": 3,
        "w": 1.908152706989274,
        "x": 76.44022796226325,
        "y": 19.44672110528279,
        "z": -1.193000897866016,
        "framename": "frame0059",
        "groupname": "20221224_group0058_mode2_88frames"
    },
    {
        "alpha": -1.547564372498891,
        "class": "car",
        "h": 1.526112672888546,
        "l": 4.678088050514741,
        "motion": 1,
        "object_id": "133",
        "occluded": 0,
        "truncated": 0,
        "w": 2.120239589188475,
        "x": -19.14168690291277,
        "y": 39.57605028619053,
        "z": -1.330482161495389,
        "framename": "frame0059",
        "groupname": "20221224_group0058_mode2_88frames"
    },
    {
        "alpha": -3.129234755980088,
        "class": "car",
        "h": 1.690504195010276,
        "l": 4.478114138352565,
        "motion": 0,
        "object_id": "134",
        "occluded": 3,
        "truncated": 3,
        "w": 1.908152706989274,
        "x": 67.86965783618095,
        "y": 11.20864434443936,
        "z": -1.332399991398064,
        "framename": "frame0059",
        "groupname": "20221224_group0058_mode2_88frames"
    },
    {
        "alpha": 0.01235789760970726,
        "class": "car",
        "h": 1.43171096021858,
        "l": 4.478114138352565,
        "motion": 0,
        "object_id": "135",
        "occluded": 3,
        "truncated": 3,
        "w": 1.908152706989274,
        "x": 45.4062193142291,
        "y": 18.52921887469166,
        "z": -1.520926347674,
        "framename": "frame0059",
        "groupname": "20221224_group0058_mode2_88frames"
    },
    {
        "alpha": -0.0109939195352056,
        "class": "car",
        "h": 1.556933493182304,
        "l": 4.373668327545507,
        "motion": 0,
        "object_id": "136",
        "occluded": 3,
        "truncated": 3,
        "w": 1.908152706989275,
        "x": 71.338613599657,
        "y": 19.68786384386975,
        "z": -1.125531095850565,
        "framename": "frame0059",
        "groupname": "20221224_group0058_mode2_88frames"
    },
    {
        "alpha": 2.175826443054097,
        "class": "car",
        "h": 1.917953288416346,
        "l": 4.678088050514742,
        "motion": 0,
        "object_id": "150",
        "occluded": 3,
        "truncated": 3,
        "w": 1.8953529025679,
        "x": -64.7915199258904,
        "y": 48.9458017343468,
        "z": -1.916837426600384,
        "framename": "frame0059",
        "groupname": "20221224_group0058_mode2_88frames"
    },
    {
        "alpha": 1.577042256180523,
        "class": "car",
        "h": 1.821946620846446,
        "l": 4.478114138352565,
        "motion": 0,
        "object_id": "153",
        "occluded": 3,
        "truncated": 3,
        "w": 1.908152706989274,
        "x": -70.0331457449956,
        "y": 71.06782018417405,
        "z": -1.531009931255584,
        "framename": "frame0059",
        "groupname": "20221224_group0058_mode2_88frames"
    },
    {
        "alpha": 0.04988728200259353,
        "class": "car",
        "h": 1.560797990789539,
        "l": 4.556677544288573,
        "motion": 1,
        "object_id": "160",
        "occluded": 3,
        "truncated": 3,
        "w": 1.908152706989274,
        "x": -79.28370963703738,
        "y": 27.03685378942994,
        "z": -2.51090087160975,
        "framename": "frame0059",
        "groupname": "20221224_group0058_mode2_88frames"
    },
    {
        "alpha": 1.577042256180523,
        "class": "car",
        "h": 1.566054384369157,
        "l": 4.478114138352565,
        "motion": 0,
        "object_id": "162",
        "occluded": 3,
        "truncated": 3,
        "w": 1.908152706989274,
        "x": -66.58531144409336,
        "y": 70.70778913845047,
        "z": -1.705950285113061,
        "framename": "frame0059",
        "groupname": "20221224_group0058_mode2_88frames"
    },
    {
        "alpha": 3.117163089118832,
        "class": "car",
        "h": 1.981951186119343,
        "l": 4.615893256634957,
        "motion": 0,
        "object_id": "163",
        "occluded": 3,
        "truncated": 3,
        "w": 2.000605240452568,
        "x": -60.35686547320467,
        "y": 83.1028993525805,
        "z": -1.036686633310527,
        "framename": "frame0059",
        "groupname": "20221224_group0058_mode2_88frames"
    },
    {
        "alpha": 3.057485427648575,
        "class": "car",
        "h": 1.522829050375778,
        "l": 4.373668327545506,
        "motion": 1,
        "object_id": "170",
        "occluded": 3,
        "truncated": 3,
        "w": 1.908152706989274,
        "x": 86.2633594440698,
        "y": 49.30192247012953,
        "z": -0.8944864799355517,
        "framename": "frame0059",
        "groupname": "20221224_group0058_mode2_88frames"
    },
    {
        "alpha": -3.129234755980087,
        "class": "car",
        "h": 1.453932179382016,
        "l": 4.478114138352565,
        "motion": 0,
        "object_id": "185",
        "occluded": 3,
        "truncated": 3,
        "w": 1.908152706989274,
        "x": 81.76900531702053,
        "y": 11.66564439850492,
        "z": -1.442522719144161,
        "framename": "frame0059",
        "groupname": "20221224_group0058_mode2_88frames"
    }
]