[
    {
        "alpha": 1.629066074532032,
        "class": "car",
        "h": 1.660263279476903,
        "l": 4.218131024944757,
        "motion": 1,
        "object_id": "1",
        "occluded": 0,
        "truncated": 0,
        "w": 2.019011097282251,
        "x": -2.745735220307191,
        "y": 62.34219586792532,
        "z": -2.925351045775812,
        "framename": "frame0386",
        "groupname": "20221219_group0015_mode2_469frames"
    },
    {
        "alpha": 1.639202089833083,
        "class": "motorcyclist",
        "h": 1.61358416902068,
        "l": 1.846025146530001,
        "motion": 1,
        "object_id": "3",
        "occluded": 3,
        "truncated": 3,
        "w": 0.8872545223791878,
        "x": 13.22652935372756,
        "y": 1.849262868173082,
        "z": -1.391015938994145,
        "framename": "frame0386",
        "groupname": "20221219_group0015_mode2_469frames"
    },
    {
        "alpha": 1.671689359174431,
        "class": "motorcyclist",
        "h": 1.70854828028181,
        "l": 1.963350350326179,
        "motion": 1,
        "object_id": "4",
        "occluded": 0,
        "truncated": 0,
        "w": 0.8721671261168946,
        "x": 12.06499485834702,
        "y": 43.60939456807125,
        "z": -2.405950793711595,
        "framename": "frame0386",
        "groupname": "20221219_group0015_mode2_469frames"
    },
    {
        "alpha": 1.582600580888434,
        "class": "car",
        "h": 2.046523063863766,
        "l": 4.803105516651481,
        "motion": 1,
        "object_id": "22",
        "occluded": 0,
        "truncated": 0,
        "w": 2.133102432397785,
        "x": 2.4248342549627,
        "y": 97.19052661424695,
        "z": -3.459749717655564,
        "framename": "frame0386",
        "groupname": "20221219_group0015_mode2_469frames"
    },
    {
        "alpha": 1.654188175448234,
        "class": "car",
        "h": 1.535061005270471,
        "l": 4.255999035878626,
        "motion": 1,
        "object_id": "36",
        "occluded": 0,
        "truncated": 0,
        "w": 1.884601669467549,
        "x": 1.890828714717643,
        "y": 45.76164425606311,
        "z": -2.540128792365021,
        "framename": "frame0386",
        "groupname": "20221219_group0015_mode2_469frames"
    }
]